{"ibge": 3125804, "codufmun": "312580", "fonte": "cnes_st_mg_202603.parquet", "total_no_municipio": 13, "total_relevante_generalista": 6, "por_tipo": {"Consultório Isolado": 5, "Centro de Saúde / UBS": 1}, "estabelecimentos": [{"cnes": "5774241", "tp_unid_cod": "22", "tp_unid": "Consultório Isolado", "cnpj": "48700755000125", "cnpj_mantenedora": "00000000000000", "cep": "35135000", "atende_sus": "0", "atendimento_ambulatorial": "1", "atendimento_hospitalar": "0", "urgencia_emergencia": "0", "natureza_juridica": "2135", "nome": "MACHADO ODONTOLOGIA ESPECIALIZADA"}, {"cnes": "5774292", "tp_unid_cod": "22", "tp_unid": "Consultório Isolado", "cnpj": "00008562765619", "cnpj_mantenedora": "00000000000000", "cep": "35135000", "atende_sus": "0", "atendimento_ambulatorial": "1", "atendimento_hospitalar": "0", "urgencia_emergencia": "0", "natureza_juridica": "4000", "nome": "JOSIMAR COSTA FISIOTERAPIA"}, {"cnes": "5774314", "tp_unid_cod": "22", "tp_unid": "Consultório Isolado", "cnpj": "00011447254619", "cnpj_mantenedora": "00000000000000", "cep": "35135000", "atende_sus": "0", "atendimento_ambulatorial": "1", "atendimento_hospitalar": "0", "urgencia_emergencia": "0", "natureza_juridica": "4000", "nome": "RAYANE ALVES FISIOTERAPIA"}, {"cnes": "5774330", "tp_unid_cod": "22", "tp_unid": "Consultório Isolado", "cnpj": "00000353326623", "cnpj_mantenedora": "00000000000000", "cep": "35135000", "atende_sus": "0", "atendimento_ambulatorial": "1", "atendimento_hospitalar": "0", "urgencia_emergencia": "0", "natureza_juridica": "4000", "nome": "CONSULTORIO ODONTOLOGICO WAGNER RAIMUNDO BARBOSA"}, {"cnes": "7459629", "tp_unid_cod": "02", "tp_unid": "Centro de Saúde / UBS", "cnpj": "00000000000000", "cnpj_mantenedora": "18080887000130", "cep": "35135000", "atende_sus": "1", "atendimento_ambulatorial": "1", "atendimento_hospitalar": "0", "urgencia_emergencia": "0", "natureza_juridica": "1244", "nome": "PSF MARIA AUXILIADORA DA SILVA"}, {"cnes": "8092494", "tp_unid_cod": "22", "tp_unid": "Consultório Isolado", "cnpj": "51203226000120", "cnpj_mantenedora": "00000000000000", "cep": "35135000", "atende_sus": "0", "atendimento_ambulatorial": "1", "atendimento_hospitalar": "0", "urgencia_emergencia": "0", "natureza_juridica": "2062", "nome": "HUGO MOREIRA RAMOS LTDA"}]}