{"ibge": 3135209, "codufmun": "313520", "fonte": "cnes_st_mg_202603.parquet", "total_no_municipio": 167, "total_relevante_generalista": 132, "por_tipo": {"Clínica/Centro de Especialidade": 63, "Consultório Isolado": 45, "Centro de Saúde / UBS": 23, "Hospital Geral": 1}, "estabelecimentos": [{"cnes": "0109088", "tp_unid_cod": "36", "tp_unid": "Clínica/Centro de Especialidade", "cnpj": "34974148000149", "cnpj_mantenedora": "00000000000000", "cep": "39480000", "atende_sus": "0", "atendimento_ambulatorial": "1", "atendimento_hospitalar": "0", "urgencia_emergencia": "0", "natureza_juridica": "2062", "nome": "VM CLINICA ODONTOLOGICA E PSICOLOGICA LTDA"}, {"cnes": "0155837", "tp_unid_cod": "36", "tp_unid": "Clínica/Centro de Especialidade", "cnpj": "31732189000130", "cnpj_mantenedora": "00000000000000", "cep": "39480000", "atende_sus": "1", "atendimento_ambulatorial": "1", "atendimento_hospitalar": "0", "urgencia_emergencia": "0", "natureza_juridica": "2062", "nome": "RESSONAR IMAGENS MEDICAS"}, {"cnes": "0163910", "tp_unid_cod": "22", "tp_unid": "Consultório Isolado", "cnpj": "21372990000169", "cnpj_mantenedora": "00000000000000", "cep": "39480000", "atende_sus": "1", "atendimento_ambulatorial": "1", "atendimento_hospitalar": "0", "urgencia_emergencia": "0", "natureza_juridica": "3999", "nome": "ABRIGO LAR DE JESUS"}, {"cnes": "0175137", "tp_unid_cod": "02", "tp_unid": "Centro de Saúde / UBS", "cnpj": "00000000000000", "cnpj_mantenedora": "21461546000110", "cep": "39480000", "atende_sus": "1", "atendimento_ambulatorial": "1", "atendimento_hospitalar": "0", "urgencia_emergencia": "0", "natureza_juridica": "1244", "nome": "CEDRI CENTRO ESPECIALIZADO EM DOENCAS RESPIRATORIAS E INFECT"}, {"cnes": "0185930", "tp_unid_cod": "36", "tp_unid": "Clínica/Centro de Especialidade", "cnpj": "10926310000195", "cnpj_mantenedora": "00000000000000", "cep": "39480000", "atende_sus": "0", "atendimento_ambulatorial": "1", "atendimento_hospitalar": "0", "urgencia_emergencia": "0", "natureza_juridica": "2062", "nome": "CIAMED CLINICA MEDICA ANTUNES E DOURADO LTDA"}, {"cnes": "0247979", "tp_unid_cod": "36", "tp_unid": "Clínica/Centro de Especialidade", "cnpj": "37258668000143", "cnpj_mantenedora": "00000000000000", "cep": "39480000", "atende_sus": "0", "atendimento_ambulatorial": "1", "atendimento_hospitalar": "0", "urgencia_emergencia": "0", "natureza_juridica": "2062", "nome": "AVR CONSULTORIO MEDICO"}, {"cnes": "0704784", "tp_unid_cod": "36", "tp_unid": "Clínica/Centro de Especialidade", "cnpj": "40838561000189", "cnpj_mantenedora": "00000000000000", "cep": "39480000", "atende_sus": "0", "atendimento_ambulatorial": "1", "atendimento_hospitalar": "0", "urgencia_emergencia": "0", "natureza_juridica": "2062", "nome": "MORO FREIRE MEDICINA"}, {"cnes": "0772380", "tp_unid_cod": "36", "tp_unid": "Clínica/Centro de Especialidade", "cnpj": "00000000000000", "cnpj_mantenedora": "16695025000197", "cep": "39480000", "atende_sus": "0", "atendimento_ambulatorial": "1", "atendimento_hospitalar": "0", "urgencia_emergencia": "0", "natureza_juridica": "1023", "nome": "30 BATALHAO DE PMMG SECAO DE ASSISTENCIA A SAUDE"}, {"cnes": "0859451", "tp_unid_cod": "36", "tp_unid": "Clínica/Centro de Especialidade", "cnpj": "28662718000162", "cnpj_mantenedora": "00000000000000", "cep": "39480000", "atende_sus": "0", "atendimento_ambulatorial": "1", "atendimento_hospitalar": "0", "urgencia_emergencia": "0", "natureza_juridica": "2062", "nome": "REABILITAR CLINICA DE FISIOTERAPIA"}, {"cnes": "0859486", "tp_unid_cod": "36", "tp_unid": "Clínica/Centro de Especialidade", "cnpj": "42651404000195", "cnpj_mantenedora": "00000000000000", "cep": "39480000", "atende_sus": "0", "atendimento_ambulatorial": "1", "atendimento_hospitalar": "0", "urgencia_emergencia": "0", "natureza_juridica": "2062", "nome": "LAUGHTON ROCHA OFTALMOLOGIA LTDA"}, {"cnes": "0969419", "tp_unid_cod": "36", "tp_unid": "Clínica/Centro de Especialidade", "cnpj": "41824797000129", "cnpj_mantenedora": "00000000000000", "cep": "39480000", "atende_sus": "0", "atendimento_ambulatorial": "1", "atendimento_hospitalar": "0", "urgencia_emergencia": "0", "natureza_juridica": "2062", "nome": "CLINICA DAIANE TEIXEIRA"}, {"cnes": "2104229", "tp_unid_cod": "02", "tp_unid": "Centro de Saúde / UBS", "cnpj": "00000000000000", "cnpj_mantenedora": "21461546000110", "cep": "39480000", "atende_sus": "1", "atendimento_ambulatorial": "1", "atendimento_hospitalar": "0", "urgencia_emergencia": "0", "natureza_juridica": "1244", "nome": "UBS BREJO DO AMPARO"}, {"cnes": "2104288", "tp_unid_cod": "02", "tp_unid": "Centro de Saúde / UBS", "cnpj": "00000000000000", "cnpj_mantenedora": "21461546000110", "cep": "39480000", "atende_sus": "1", "atendimento_ambulatorial": "1", "atendimento_hospitalar": "0", "urgencia_emergencia": "0", "natureza_juridica": "1244", "nome": "UBS PANDEIROS"}, {"cnes": "2104393", "tp_unid_cod": "02", "tp_unid": "Centro de Saúde / UBS", "cnpj": "00000000000000", "cnpj_mantenedora": "21461546000110", "cep": "39480000", "atende_sus": "1", "atendimento_ambulatorial": "1", "atendimento_hospitalar": "0", "urgencia_emergencia": "0", "natureza_juridica": "1244", "nome": "UBS CAIC"}, {"cnes": "2104407", "tp_unid_cod": "02", "tp_unid": "Centro de Saúde / UBS", "cnpj": "00000000000000", "cnpj_mantenedora": "21461546000110", "cep": "39480000", "atende_sus": "1", "atendimento_ambulatorial": "1", "atendimento_hospitalar": "0", "urgencia_emergencia": "0", "natureza_juridica": "1244", "nome": "UBS LEVIANOPOLIS"}, {"cnes": "2204223", "tp_unid_cod": "02", "tp_unid": "Centro de Saúde / UBS", "cnpj": "00000000000000", "cnpj_mantenedora": "21461546000110", "cep": "39480000", "atende_sus": "1", "atendimento_ambulatorial": "1", "atendimento_hospitalar": "0", "urgencia_emergencia": "0", "natureza_juridica": "1244", "nome": "UBS BARAO DE SAO ROMAO"}, {"cnes": "2204258", "tp_unid_cod": "02", "tp_unid": "Centro de Saúde / UBS", "cnpj": "00000000000000", "cnpj_mantenedora": "21461546000110", "cep": "39480000", "atende_sus": "1", "atendimento_ambulatorial": "1", "atendimento_hospitalar": "0", "urgencia_emergencia": "0", "natureza_juridica": "1244", "nome": "UBS VARZEA BONITA"}, {"cnes": "2204266", "tp_unid_cod": "02", "tp_unid": "Centro de Saúde / UBS", "cnpj": "00000000000000", "cnpj_mantenedora": "21461546000110", "cep": "39480000", "atende_sus": "1", "atendimento_ambulatorial": "1", "atendimento_hospitalar": "0", "urgencia_emergencia": "0", "natureza_juridica": "1244", "nome": "UBS FABIAO I"}, {"cnes": "2204274", "tp_unid_cod": "02", "tp_unid": "Centro de Saúde / UBS", "cnpj": "00000000000000", "cnpj_mantenedora": "21461546000110", "cep": "39480000", "atende_sus": "1", "atendimento_ambulatorial": "1", "atendimento_hospitalar": "0", "urgencia_emergencia": "0", "natureza_juridica": "1244", "nome": "UBS DE BOM JARDIM"}, {"cnes": "2204290", "tp_unid_cod": "02", "tp_unid": "Centro de Saúde / UBS", "cnpj": "00000000000000", "cnpj_mantenedora": "21461546000110", "cep": "39480000", "atende_sus": "1", "atendimento_ambulatorial": "1", "atendimento_hospitalar": "0", "urgencia_emergencia": "0", "natureza_juridica": "1244", "nome": "UBS SAO JOAQUIM"}, {"cnes": "2204312", "tp_unid_cod": "02", "tp_unid": "Centro de Saúde / UBS", "cnpj": "00000000000000", "cnpj_mantenedora": "21461546000110", "cep": "39480000", "atende_sus": "1", "atendimento_ambulatorial": "1", "atendimento_hospitalar": "0", "urgencia_emergencia": "0", "natureza_juridica": "1244", "nome": "UBS BOA VISTA"}, {"cnes": "2204320", "tp_unid_cod": "02", "tp_unid": "Centro de Saúde / UBS", "cnpj": "00000000000000", "cnpj_mantenedora": "21461546000110", "cep": "39480000", "atende_sus": "1", "atendimento_ambulatorial": "1", "atendimento_hospitalar": "0", "urgencia_emergencia": "0", "natureza_juridica": "1244", "nome": "UBS RIACHO DA CRUZ"}, {"cnes": "2204363", "tp_unid_cod": "02", "tp_unid": "Centro de Saúde / UBS", "cnpj": "00000000000000", "cnpj_mantenedora": "21461546000110", "cep": "39480000", "atende_sus": "1", "atendimento_ambulatorial": "1", "atendimento_hospitalar": "0", "urgencia_emergencia": "0", "natureza_juridica": "1244", "nome": "UBS TEJUCO"}, {"cnes": "2204371", "tp_unid_cod": "02", "tp_unid": "Centro de Saúde / UBS", "cnpj": "00000000000000", "cnpj_mantenedora": "21461546000110", "cep": "39480000", "atende_sus": "1", "atendimento_ambulatorial": "1", "atendimento_hospitalar": "0", "urgencia_emergencia": "0", "natureza_juridica": "1244", "nome": "UBS DR AURELIO CACIQUINHO FERREIRA SESC"}, {"cnes": "2204398", "tp_unid_cod": "36", "tp_unid": "Clínica/Centro de Especialidade", "cnpj": "01978837000172", "cnpj_mantenedora": "00000000000000", "cep": "39480000", "atende_sus": "1", "atendimento_ambulatorial": "1", "atendimento_hospitalar": "0", "urgencia_emergencia": "0", "natureza_juridica": "3999", "nome": "CER II CENTRO ESPECIALIZADO EM REABILITACAO"}, {"cnes": "2204622", "tp_unid_cod": "05", "tp_unid": "Hospital Geral", "cnpj": "00000000000000", "cnpj_mantenedora": "21461546000110", "cep": "39480000", "atende_sus": "1", "atendimento_ambulatorial": "1", "atendimento_hospitalar": "1", "urgencia_emergencia": "1", "natureza_juridica": "1244", "nome": "HOSPITAL MUNICIPAL DE JANUARIA"}, {"cnes": "2768372", "tp_unid_cod": "02", "tp_unid": "Centro de Saúde / UBS", "cnpj": "00000000000000", "cnpj_mantenedora": "21461546000110", "cep": "39480000", "atende_sus": "1", "atendimento_ambulatorial": "1", "atendimento_hospitalar": "0", "urgencia_emergencia": "0", "natureza_juridica": "1244", "nome": "UBS AURORA DIAS DA SILVA"}, {"cnes": "2768380", "tp_unid_cod": "02", "tp_unid": "Centro de Saúde / UBS", "cnpj": "00000000000000", "cnpj_mantenedora": "21461546000110", "cep": "39480000", "atende_sus": "1", "atendimento_ambulatorial": "1", "atendimento_hospitalar": "0", "urgencia_emergencia": "0", "natureza_juridica": "1244", "nome": "UBS PADRE ALFONSO MUER"}, {"cnes": "2772477", "tp_unid_cod": "02", "tp_unid": "Centro de Saúde / UBS", "cnpj": "00000000000000", "cnpj_mantenedora": "21461546000110", "cep": "39480000", "atende_sus": "1", "atendimento_ambulatorial": "1", "atendimento_hospitalar": "0", "urgencia_emergencia": "0", "natureza_juridica": "1244", "nome": "UBS HERNESTO SOARES DOS REIS SR TININ"}, {"cnes": "2848082", "tp_unid_cod": "22", "tp_unid": "Consultório Isolado", "cnpj": "24797925000173", "cnpj_mantenedora": "00000000000000", "cep": "39480000", "atende_sus": "0", "atendimento_ambulatorial": "1", "atendimento_hospitalar": "0", "urgencia_emergencia": "0", "natureza_juridica": "2062", "nome": "VB POSTO DE MEDICAMENTOS"}, {"cnes": "2867419", "tp_unid_cod": "36", "tp_unid": "Clínica/Centro de Especialidade", "cnpj": "14391716000171", "cnpj_mantenedora": "00000000000000", "cep": "39480000", "atende_sus": "1", "atendimento_ambulatorial": "1", "atendimento_hospitalar": "0", "urgencia_emergencia": "0", "natureza_juridica": "2062", "nome": "EUALDO FERNANDES ENDOCRINOLOGIA E SERVICOS MEDICOS"}, {"cnes": "2909650", "tp_unid_cod": "36", "tp_unid": "Clínica/Centro de Especialidade", "cnpj": "17888365000105", "cnpj_mantenedora": "00000000000000", "cep": "39480000", "atende_sus": "0", "atendimento_ambulatorial": "1", "atendimento_hospitalar": "0", "urgencia_emergencia": "0", "natureza_juridica": "2062", "nome": "CENTRO MEDICO MAIS VIDA"}, {"cnes": "2965542", "tp_unid_cod": "36", "tp_unid": "Clínica/Centro de Especialidade", "cnpj": "46178637000173", "cnpj_mantenedora": "00000000000000", "cep": "39480000", "atende_sus": "0", "atendimento_ambulatorial": "1", "atendimento_hospitalar": "0", "urgencia_emergencia": "0", "natureza_juridica": "2062", "nome": "CLINICA ODONTOLOGICA HARMONIZE"}, {"cnes": "2985381", "tp_unid_cod": "22", "tp_unid": "Consultório Isolado", "cnpj": "00006206333604", "cnpj_mantenedora": "00000000000000", "cep": "39480000", "atende_sus": "0", "atendimento_ambulatorial": "1", "atendimento_hospitalar": "0", "urgencia_emergencia": "0", "natureza_juridica": "4000", "nome": "LAIS ALMEIDA"}, {"cnes": "4045769", "tp_unid_cod": "36", "tp_unid": "Clínica/Centro de Especialidade", "cnpj": "37337502000112", "cnpj_mantenedora": "00000000000000", "cep": "39480000", "atende_sus": "1", "atendimento_ambulatorial": "1", "atendimento_hospitalar": "0", "urgencia_emergencia": "0", "natureza_juridica": "2062", "nome": "FSCB OFTALMOLIGIA"}, {"cnes": "4079833", "tp_unid_cod": "36", "tp_unid": "Clínica/Centro de Especialidade", "cnpj": "48347708000140", "cnpj_mantenedora": "00000000000000", "cep": "39480000", "atende_sus": "0", "atendimento_ambulatorial": "1", "atendimento_hospitalar": "0", "urgencia_emergencia": "0", "natureza_juridica": "2062", "nome": "CLINICA CORPUS FISIOTERAPIA ESTETICA E SERVICOS LTDA"}, {"cnes": "4100832", "tp_unid_cod": "36", "tp_unid": "Clínica/Centro de Especialidade", "cnpj": "48885880000157", "cnpj_mantenedora": "00000000000000", "cep": "39480000", "atende_sus": "0", "atendimento_ambulatorial": "1", "atendimento_hospitalar": "0", "urgencia_emergencia": "0", "natureza_juridica": "2062", "nome": "DANIEL ANDRADA PEDIATRA"}, {"cnes": "4224256", "tp_unid_cod": "02", "tp_unid": "Centro de Saúde / UBS", "cnpj": "00000000000000", "cnpj_mantenedora": "21461546000110", "cep": "39480000", "atende_sus": "1", "atendimento_ambulatorial": "1", "atendimento_hospitalar": "0", "urgencia_emergencia": "0", "natureza_juridica": "1244", "nome": "SERVICO MUNICIPAL DE FISIOTERAPIA"}, {"cnes": "4425863", "tp_unid_cod": "36", "tp_unid": "Clínica/Centro de Especialidade", "cnpj": "48974170000101", "cnpj_mantenedora": "00000000000000", "cep": "39480000", "atende_sus": "1", "atendimento_ambulatorial": "1", "atendimento_hospitalar": "0", "urgencia_emergencia": "0", "natureza_juridica": "2062", "nome": "CLINICA OFTALMOLOGICA DR LUCIANO NASSER"}, {"cnes": "4505468", "tp_unid_cod": "36", "tp_unid": "Clínica/Centro de Especialidade", "cnpj": "40829891000108", "cnpj_mantenedora": "00000000000000", "cep": "39480000", "atende_sus": "0", "atendimento_ambulatorial": "1", "atendimento_hospitalar": "0", "urgencia_emergencia": "0", "natureza_juridica": "2062", "nome": "E A DE SOUZA AMARO LTDA"}, {"cnes": "4725921", "tp_unid_cod": "22", "tp_unid": "Consultório Isolado", "cnpj": "19076181000168", "cnpj_mantenedora": "00000000000000", "cep": "39480000", "atende_sus": "1", "atendimento_ambulatorial": "1", "atendimento_hospitalar": "0", "urgencia_emergencia": "0", "natureza_juridica": "2062", "nome": "OTICAS JANUARIA"}, {"cnes": "4852583", "tp_unid_cod": "36", "tp_unid": "Clínica/Centro de Especialidade", "cnpj": "56981973000103", "cnpj_mantenedora": "00000000000000", "cep": "39480000", "atende_sus": "0", "atendimento_ambulatorial": "1", "atendimento_hospitalar": "0", "urgencia_emergencia": "0", "natureza_juridica": "2135", "nome": "VANESSA RODRIGUES PINTO"}, {"cnes": "5049067", "tp_unid_cod": "36", "tp_unid": "Clínica/Centro de Especialidade", "cnpj": "08043696000145", "cnpj_mantenedora": "00000000000000", "cep": "39480000", "atende_sus": "1", "atendimento_ambulatorial": "1", "atendimento_hospitalar": "0", "urgencia_emergencia": "0", "natureza_juridica": "2240", "nome": "CLINICA MEDICA ANDERSON AGOSTINHO MALHEIRO"}, {"cnes": "5137772", "tp_unid_cod": "36", "tp_unid": "Clínica/Centro de Especialidade", "cnpj": "08333710000145", "cnpj_mantenedora": "00000000000000", "cep": "39480000", "atende_sus": "0", "atendimento_ambulatorial": "1", "atendimento_hospitalar": "0", "urgencia_emergencia": "0", "natureza_juridica": "2062", "nome": "CLINICA DE FISIOTERAPIA FISIOJAN"}, {"cnes": "5184533", "tp_unid_cod": "22", "tp_unid": "Consultório Isolado", "cnpj": "02200001000105", "cnpj_mantenedora": "00000000000000", "cep": "39480000", "atende_sus": "0", "atendimento_ambulatorial": "1", "atendimento_hospitalar": "0", "urgencia_emergencia": "0", "natureza_juridica": "2240", "nome": "CLINICA MEDICA CASTRO AZEVEDO"}, {"cnes": "5184614", "tp_unid_cod": "22", "tp_unid": "Consultório Isolado", "cnpj": "00052699650625", "cnpj_mantenedora": "00000000000000", "cep": "39480000", "atende_sus": "0", "atendimento_ambulatorial": "1", "atendimento_hospitalar": "0", "urgencia_emergencia": "1", "natureza_juridica": "4000", "nome": "CLINICA PEDIATRICA PATRICIA MARIA FERNANDES BRANT"}, {"cnes": "5184630", "tp_unid_cod": "22", "tp_unid": "Consultório Isolado", "cnpj": "01510331000134", "cnpj_mantenedora": "00000000000000", "cep": "39480000", "atende_sus": "0", "atendimento_ambulatorial": "1", "atendimento_hospitalar": "0", "urgencia_emergencia": "0", "natureza_juridica": "2062", "nome": "CLINICA CARDIOLOGICA CARDIOJAN"}, {"cnes": "5184657", "tp_unid_cod": "22", "tp_unid": "Consultório Isolado", "cnpj": "00082243131668", "cnpj_mantenedora": "00000000000000", "cep": "39480000", "atende_sus": "0", "atendimento_ambulatorial": "1", "atendimento_hospitalar": "0", "urgencia_emergencia": "0", "natureza_juridica": "4000", "nome": "CLINICA OFTALMOLOGICA SILVIO JOSE BICALHO SILVEIRA"}, {"cnes": "5202698", "tp_unid_cod": "36", "tp_unid": "Clínica/Centro de Especialidade", "cnpj": "03050206000114", "cnpj_mantenedora": "00000000000000", "cep": "39480000", "atende_sus": "1", "atendimento_ambulatorial": "1", "atendimento_hospitalar": "0", "urgencia_emergencia": "1", "natureza_juridica": "2062", "nome": "CLINICA COLARES LTDA"}, {"cnes": "5284775", "tp_unid_cod": "36", "tp_unid": "Clínica/Centro de Especialidade", "cnpj": "07987380000149", "cnpj_mantenedora": "00000000000000", "cep": "39480000", "atende_sus": "0", "atendimento_ambulatorial": "1", "atendimento_hospitalar": "0", "urgencia_emergencia": "1", "natureza_juridica": "2240", "nome": "CLINICA ODONTOLOGICA DOMICIANO"}, {"cnes": "5307759", "tp_unid_cod": "36", "tp_unid": "Clínica/Centro de Especialidade", "cnpj": "08107819000164", "cnpj_mantenedora": "00000000000000", "cep": "39480000", "atende_sus": "0", "atendimento_ambulatorial": "1", "atendimento_hospitalar": "0", "urgencia_emergencia": "0", "natureza_juridica": "2062", "nome": "CLINICA CARDIOLOGICA BRASIL MARTINS SERVICOS MEDICOS"}, {"cnes": "5426685", "tp_unid_cod": "36", "tp_unid": "Clínica/Centro de Especialidade", "cnpj": "05110783000180", "cnpj_mantenedora": "00000000000000", "cep": "39480000", "atende_sus": "0", "atendimento_ambulatorial": "1", "atendimento_hospitalar": "0", "urgencia_emergencia": "0", "natureza_juridica": "2240", "nome": "CIMEG"}, {"cnes": "5426715", "tp_unid_cod": "22", "tp_unid": "Consultório Isolado", "cnpj": "00009069607620", "cnpj_mantenedora": "00000000000000", "cep": "39480000", "atende_sus": "0", "atendimento_ambulatorial": "1", "atendimento_hospitalar": "0", "urgencia_emergencia": "0", "natureza_juridica": "4000", "nome": "ALCIR FERNANDO DE MATOS"}, {"cnes": "5432294", "tp_unid_cod": "36", "tp_unid": "Clínica/Centro de Especialidade", "cnpj": "04388521000119", "cnpj_mantenedora": "00000000000000", "cep": "39480000", "atende_sus": "1", "atendimento_ambulatorial": "1", "atendimento_hospitalar": "0", "urgencia_emergencia": "0", "natureza_juridica": "2062", "nome": "MED CENTER"}, {"cnes": "5501776", "tp_unid_cod": "36", "tp_unid": "Clínica/Centro de Especialidade", "cnpj": "08993308000197", "cnpj_mantenedora": "00000000000000", "cep": "39480000", "atende_sus": "1", "atendimento_ambulatorial": "1", "atendimento_hospitalar": "0", "urgencia_emergencia": "1", "natureza_juridica": "2240", "nome": "INSTITUTO DE ORTOPEDIA E TRAUMATOLOGIA"}, {"cnes": "5567033", "tp_unid_cod": "22", "tp_unid": "Consultório Isolado", "cnpj": "00008239020640", "cnpj_mantenedora": "00000000000000", "cep": "39480000", "atende_sus": "0", "atendimento_ambulatorial": "1", "atendimento_hospitalar": "0", "urgencia_emergencia": "0", "natureza_juridica": "4000", "nome": "KEZIA FLAVIANE LOPES MALTA"}, {"cnes": "5596033", "tp_unid_cod": "22", "tp_unid": "Consultório Isolado", "cnpj": "00005945746681", "cnpj_mantenedora": "00000000000000", "cep": "39480000", "atende_sus": "0", "atendimento_ambulatorial": "1", "atendimento_hospitalar": "0", "urgencia_emergencia": "0", "natureza_juridica": "4000", "nome": "CARLA MOURA DE ASSIS"}, {"cnes": "5596076", "tp_unid_cod": "36", "tp_unid": "Clínica/Centro de Especialidade", "cnpj": "03062986000112", "cnpj_mantenedora": "00000000000000", "cep": "39480000", "atende_sus": "0", "atendimento_ambulatorial": "1", "atendimento_hospitalar": "0", "urgencia_emergencia": "0", "natureza_juridica": "2062", "nome": "CLINICA CALDEIRA BRANT LTDA"}, {"cnes": "5623227", "tp_unid_cod": "36", "tp_unid": "Clínica/Centro de Especialidade", "cnpj": "60606394000158", "cnpj_mantenedora": "00000000000000", "cep": "39480000", "atende_sus": "1", "atendimento_ambulatorial": "1", "atendimento_hospitalar": "0", "urgencia_emergencia": "0", "natureza_juridica": "2062", "nome": "NEURO EQUILIBRIO TERAPIAS"}, {"cnes": "5693497", "tp_unid_cod": "22", "tp_unid": "Consultório Isolado", "cnpj": "00007278927625", "cnpj_mantenedora": "00000000000000", "cep": "39480000", "atende_sus": "0", "atendimento_ambulatorial": "1", "atendimento_hospitalar": "0", "urgencia_emergencia": "0", "natureza_juridica": "4000", "nome": "LILIANE DE OLIVEIRA MELO"}, {"cnes": "5723736", "tp_unid_cod": "22", "tp_unid": "Consultório Isolado", "cnpj": "00073416428668", "cnpj_mantenedora": "00000000000000", "cep": "39480000", "atende_sus": "0", "atendimento_ambulatorial": "1", "atendimento_hospitalar": "0", "urgencia_emergencia": "1", "natureza_juridica": "4000", "nome": "REGINA CELIA MARTINS SOUTO"}, {"cnes": "5730910", "tp_unid_cod": "22", "tp_unid": "Consultório Isolado", "cnpj": "00001323295658", "cnpj_mantenedora": "00000000000000", "cep": "39480000", "atende_sus": "0", "atendimento_ambulatorial": "1", "atendimento_hospitalar": "0", "urgencia_emergencia": "1", "natureza_juridica": "4000", "nome": "KATIA LIDIANE COSTA DOMICIANO"}, {"cnes": "5735149", "tp_unid_cod": "22", "tp_unid": "Consultório Isolado", "cnpj": "00001228124680", "cnpj_mantenedora": "00000000000000", "cep": "39480000", "atende_sus": "0", "atendimento_ambulatorial": "1", "atendimento_hospitalar": "0", "urgencia_emergencia": "1", "natureza_juridica": "4000", "nome": "MARCELO FELIPE GUSMAO SANTIAGO"}, {"cnes": "5735211", "tp_unid_cod": "22", "tp_unid": "Consultório Isolado", "cnpj": "00005751249623", "cnpj_mantenedora": "00000000000000", "cep": "39480000", "atende_sus": "0", "atendimento_ambulatorial": "1", "atendimento_hospitalar": "0", "urgencia_emergencia": "1", "natureza_juridica": "4000", "nome": "VLADIMIR COSTA DOMICIANO"}, {"cnes": "5740363", "tp_unid_cod": "36", "tp_unid": "Clínica/Centro de Especialidade", "cnpj": "54815932000111", "cnpj_mantenedora": "00000000000000", "cep": "39480000", "atende_sus": "1", "atendimento_ambulatorial": "1", "atendimento_hospitalar": "0", "urgencia_emergencia": "0", "natureza_juridica": "2062", "nome": "CONNECT TERAPIA"}, {"cnes": "5745322", "tp_unid_cod": "36", "tp_unid": "Clínica/Centro de Especialidade", "cnpj": "22686938000140", "cnpj_mantenedora": "00000000000000", "cep": "39480000", "atende_sus": "1", "atendimento_ambulatorial": "1", "atendimento_hospitalar": "0", "urgencia_emergencia": "0", "natureza_juridica": "2062", "nome": "CLINICA FONOAUDIOLOGIA RODRIGUES LTDA"}, {"cnes": "5746949", "tp_unid_cod": "36", "tp_unid": "Clínica/Centro de Especialidade", "cnpj": "14055021000542", "cnpj_mantenedora": "00000000000000", "cep": "39480000", "atende_sus": "0", "atendimento_ambulatorial": "1", "atendimento_hospitalar": "0", "urgencia_emergencia": "0", "natureza_juridica": "2135", "nome": "OTICAS LIZ MARIA"}, {"cnes": "5770955", "tp_unid_cod": "36", "tp_unid": "Clínica/Centro de Especialidade", "cnpj": "54666362000145", "cnpj_mantenedora": "00000000000000", "cep": "39480000", "atende_sus": "0", "atendimento_ambulatorial": "1", "atendimento_hospitalar": "0", "urgencia_emergencia": "0", "natureza_juridica": "2062", "nome": "ORAL CLIN"}, {"cnes": "5793831", "tp_unid_cod": "22", "tp_unid": "Consultório Isolado", "cnpj": "07026748000102", "cnpj_mantenedora": "00000000000000", "cep": "39480000", "atende_sus": "0", "atendimento_ambulatorial": "1", "atendimento_hospitalar": "0", "urgencia_emergencia": "0", "natureza_juridica": "2135", "nome": "POSTO DE MEDICAMENTOS BOA ESPERANCA"}, {"cnes": "5797950", "tp_unid_cod": "36", "tp_unid": "Clínica/Centro de Especialidade", "cnpj": "56030100000115", "cnpj_mantenedora": "00000000000000", "cep": "39480000", "atende_sus": "0", "atendimento_ambulatorial": "1", "atendimento_hospitalar": "0", "urgencia_emergencia": "1", "natureza_juridica": "2062", "nome": "ORTHODONTIC"}, {"cnes": "5799961", "tp_unid_cod": "36", "tp_unid": "Clínica/Centro de Especialidade", "cnpj": "18146974000143", "cnpj_mantenedora": "00000000000000", "cep": "39480000", "atende_sus": "0", "atendimento_ambulatorial": "1", "atendimento_hospitalar": "0", "urgencia_emergencia": "0", "natureza_juridica": "2062", "nome": "CLINICA MEDICA E ODONTOLOGICA AVELAR"}, {"cnes": "5800978", "tp_unid_cod": "22", "tp_unid": "Consultório Isolado", "cnpj": "21280147000152", "cnpj_mantenedora": "00000000000000", "cep": "39480000", "atende_sus": "0", "atendimento_ambulatorial": "1", "atendimento_hospitalar": "0", "urgencia_emergencia": "0", "natureza_juridica": "2135", "nome": "PAMED"}, {"cnes": "5929962", "tp_unid_cod": "22", "tp_unid": "Consultório Isolado", "cnpj": "62687093000121", "cnpj_mantenedora": "00000000000000", "cep": "39480000", "atende_sus": "0", "atendimento_ambulatorial": "1", "atendimento_hospitalar": "0", "urgencia_emergencia": "0", "natureza_juridica": "2135", "nome": "KEZIA FLAVIANE LOPES MALTA"}, {"cnes": "5936969", "tp_unid_cod": "22", "tp_unid": "Consultório Isolado", "cnpj": "00004223011677", "cnpj_mantenedora": "00000000000000", "cep": "39480000", "atende_sus": "0", "atendimento_ambulatorial": "1", "atendimento_hospitalar": "0", "urgencia_emergencia": "0", "natureza_juridica": "4000", "nome": "MARCIA CRISTINA FIGUEIREDO MOTA"}, {"cnes": "5945984", "tp_unid_cod": "36", "tp_unid": "Clínica/Centro de Especialidade", "cnpj": "00000000000000", "cnpj_mantenedora": "21461546000110", "cep": "39480000", "atende_sus": "1", "atendimento_ambulatorial": "1", "atendimento_hospitalar": "0", "urgencia_emergencia": "0", "natureza_juridica": "1244", "nome": "ESPECIALIZA MINAS CEAE CATEGORIA I"}, {"cnes": "5963702", "tp_unid_cod": "36", "tp_unid": "Clínica/Centro de Especialidade", "cnpj": "35555082000115", "cnpj_mantenedora": "00000000000000", "cep": "39480000", "atende_sus": "0", "atendimento_ambulatorial": "1", "atendimento_hospitalar": "0", "urgencia_emergencia": "0", "natureza_juridica": "2062", "nome": "PRIME ASSESSORIA E MARKETING"}, {"cnes": "6019056", "tp_unid_cod": "36", "tp_unid": "Clínica/Centro de Especialidade", "cnpj": "07439640000141", "cnpj_mantenedora": "00000000000000", "cep": "39480000", "atende_sus": "0", "atendimento_ambulatorial": "1", "atendimento_hospitalar": "0", "urgencia_emergencia": "0", "natureza_juridica": "2062", "nome": "RADIOLOGICA JANUARIA"}, {"cnes": "6033407", "tp_unid_cod": "22", "tp_unid": "Consultório Isolado", "cnpj": "00080308694600", "cnpj_mantenedora": "00000000000000", "cep": "39480000", "atende_sus": "0", "atendimento_ambulatorial": "1", "atendimento_hospitalar": "0", "urgencia_emergencia": "0", "natureza_juridica": "4000", "nome": "LOURENCO ANTONIO NORMANHA MEDINA"}, {"cnes": "6192572", "tp_unid_cod": "22", "tp_unid": "Consultório Isolado", "cnpj": "00080308007620", "cnpj_mantenedora": "00000000000000", "cep": "39480000", "atende_sus": "0", "atendimento_ambulatorial": "1", "atendimento_hospitalar": "0", "urgencia_emergencia": "0", "natureza_juridica": "4000", "nome": "PRODENTE"}, {"cnes": "6228577", "tp_unid_cod": "22", "tp_unid": "Consultório Isolado", "cnpj": "00054339499668", "cnpj_mantenedora": "00000000000000", "cep": "39480000", "atende_sus": "0", "atendimento_ambulatorial": "1", "atendimento_hospitalar": "0", "urgencia_emergencia": "0", "natureza_juridica": "4000", "nome": "JOSE CARNEIRO COLARES"}, {"cnes": "6294898", "tp_unid_cod": "22", "tp_unid": "Consultório Isolado", "cnpj": "00005318024696", "cnpj_mantenedora": "00000000000000", "cep": "39480000", "atende_sus": "0", "atendimento_ambulatorial": "1", "atendimento_hospitalar": "0", "urgencia_emergencia": "0", "natureza_juridica": "4000", "nome": "JANAINA NUNNA GUEDES CAVALCANTE"}, {"cnes": "6294901", "tp_unid_cod": "22", "tp_unid": "Consultório Isolado", "cnpj": "00002548914623", "cnpj_mantenedora": "00000000000000", "cep": "39480000", "atende_sus": "0", "atendimento_ambulatorial": "1", "atendimento_hospitalar": "0", "urgencia_emergencia": "0", "natureza_juridica": "4000", "nome": "MARIJARA MAGALHAES DE CASTRO"}, {"cnes": "6332021", "tp_unid_cod": "36", "tp_unid": "Clínica/Centro de Especialidade", "cnpj": "34244776000179", "cnpj_mantenedora": "00000000000000", "cep": "39480000", "atende_sus": "0", "atendimento_ambulatorial": "1", "atendimento_hospitalar": "0", "urgencia_emergencia": "0", "natureza_juridica": "2062", "nome": "ORTOIMPLANTES NIZIO FILHO"}, {"cnes": "6337309", "tp_unid_cod": "22", "tp_unid": "Consultório Isolado", "cnpj": "00002737977606", "cnpj_mantenedora": "00000000000000", "cep": "39480000", "atende_sus": "0", "atendimento_ambulatorial": "1", "atendimento_hospitalar": "0", "urgencia_emergencia": "0", "natureza_juridica": "4000", "nome": "ALESSANDRO AGOSTINHO MALHEIRO"}, {"cnes": "6605923", "tp_unid_cod": "36", "tp_unid": "Clínica/Centro de Especialidade", "cnpj": "18645432000115", "cnpj_mantenedora": "00000000000000", "cep": "39480000", "atende_sus": "0", "atendimento_ambulatorial": "1", "atendimento_hospitalar": "0", "urgencia_emergencia": "0", "natureza_juridica": "2062", "nome": "POLICLINICA SANTA HELENA"}, {"cnes": "6650899", "tp_unid_cod": "22", "tp_unid": "Consultório Isolado", "cnpj": "00003794852907", "cnpj_mantenedora": "00000000000000", "cep": "39480000", "atende_sus": "0", "atendimento_ambulatorial": "1", "atendimento_hospitalar": "0", "urgencia_emergencia": "0", "natureza_juridica": "4000", "nome": "LIRYA LIZ MONTEIRO TONOLLI"}, {"cnes": "6651100", "tp_unid_cod": "22", "tp_unid": "Consultório Isolado", "cnpj": "00008473239601", "cnpj_mantenedora": "00000000000000", "cep": "39480000", "atende_sus": "0", "atendimento_ambulatorial": "1", "atendimento_hospitalar": "0", "urgencia_emergencia": "0", "natureza_juridica": "4000", "nome": "LUANNA FERREIRA DA SILVA"}, {"cnes": "6705863", "tp_unid_cod": "22", "tp_unid": "Consultório Isolado", "cnpj": "16893612000190", "cnpj_mantenedora": "00000000000000", "cep": "39480000", "atende_sus": "0", "atendimento_ambulatorial": "1", "atendimento_hospitalar": "0", "urgencia_emergencia": "0", "natureza_juridica": "3999", "nome": "ASILO JOAO XIII"}, {"cnes": "6772773", "tp_unid_cod": "36", "tp_unid": "Clínica/Centro de Especialidade", "cnpj": "07551961000133", "cnpj_mantenedora": "00000000000000", "cep": "39480000", "atende_sus": "0", "atendimento_ambulatorial": "1", "atendimento_hospitalar": "0", "urgencia_emergencia": "0", "natureza_juridica": "2062", "nome": "CLINICA MEDICA ARAUJO LTDA"}, {"cnes": "6784054", "tp_unid_cod": "02", "tp_unid": "Centro de Saúde / UBS", "cnpj": "00000000000000", "cnpj_mantenedora": "21461546000110", "cep": "39480000", "atende_sus": "1", "atendimento_ambulatorial": "1", "atendimento_hospitalar": "0", "urgencia_emergencia": "0", "natureza_juridica": "1244", "nome": "UBS JOVENTINA MESQUITA"}, {"cnes": "6789676", "tp_unid_cod": "22", "tp_unid": "Consultório Isolado", "cnpj": "00090671619691", "cnpj_mantenedora": "00000000000000", "cep": "39480000", "atende_sus": "0", "atendimento_ambulatorial": "1", "atendimento_hospitalar": "0", "urgencia_emergencia": "0", "natureza_juridica": "4000", "nome": "OCTAVIO HENRIQUE VEIGA ESTEVES"}, {"cnes": "6837743", "tp_unid_cod": "36", "tp_unid": "Clínica/Centro de Especialidade", "cnpj": "00000000000000", "cnpj_mantenedora": "21461546000110", "cep": "39480000", "atende_sus": "1", "atendimento_ambulatorial": "0", "atendimento_hospitalar": "0", "urgencia_emergencia": "0", "natureza_juridica": "1244", "nome": "CENTRO DE REFERENCIA EM SAUDE DO TRABALHADOR CEREST"}, {"cnes": "6841236", "tp_unid_cod": "36", "tp_unid": "Clínica/Centro de Especialidade", "cnpj": "61962515000167", "cnpj_mantenedora": "00000000000000", "cep": "39480000", "atende_sus": "0", "atendimento_ambulatorial": "1", "atendimento_hospitalar": "0", "urgencia_emergencia": "0", "natureza_juridica": "2062", "nome": "INSTITUTO DHN JOAO CRISTOVAO"}, {"cnes": "6843557", "tp_unid_cod": "22", "tp_unid": "Consultório Isolado", "cnpj": "10651808000192", "cnpj_mantenedora": "00000000000000", "cep": "39480000", "atende_sus": "0", "atendimento_ambulatorial": "1", "atendimento_hospitalar": "0", "urgencia_emergencia": "0", "natureza_juridica": "2062", "nome": "EDUARDO LUIZ FRANCA CIA LTDA"}, {"cnes": "7077068", "tp_unid_cod": "22", "tp_unid": "Consultório Isolado", "cnpj": "00005953672675", "cnpj_mantenedora": "00000000000000", "cep": "39480000", "atende_sus": "0", "atendimento_ambulatorial": "1", "atendimento_hospitalar": "0", "urgencia_emergencia": "0", "natureza_juridica": "4000", "nome": "LEANDRA OLIVEIRA TEIXEIRA"}, {"cnes": "7121547", "tp_unid_cod": "36", "tp_unid": "Clínica/Centro de Especialidade", "cnpj": "15639550000122", "cnpj_mantenedora": "00000000000000", "cep": "39480000", "atende_sus": "0", "atendimento_ambulatorial": "1", "atendimento_hospitalar": "0", "urgencia_emergencia": "0", "natureza_juridica": "2062", "nome": "LEANDRA OLIVEIRA TEIXEIRA"}, {"cnes": "7134894", "tp_unid_cod": "22", "tp_unid": "Consultório Isolado", "cnpj": "00003618621647", "cnpj_mantenedora": "00000000000000", "cep": "39480000", "atende_sus": "0", "atendimento_ambulatorial": "1", "atendimento_hospitalar": "0", "urgencia_emergencia": "0", "natureza_juridica": "4000", "nome": "CASTORINA SANTOS VIANA NETA"}, {"cnes": "7211805", "tp_unid_cod": "22", "tp_unid": "Consultório Isolado", "cnpj": "00005694934636", "cnpj_mantenedora": "00000000000000", "cep": "39480000", "atende_sus": "0", "atendimento_ambulatorial": "1", "atendimento_hospitalar": "0", "urgencia_emergencia": "0", "natureza_juridica": "4000", "nome": "IARA FABISA COSTA RODRIGUES SILVA"}, {"cnes": "7216564", "tp_unid_cod": "02", "tp_unid": "Centro de Saúde / UBS", "cnpj": "00000000000000", "cnpj_mantenedora": "05487631000109", "cep": "39480000", "atende_sus": "1", "atendimento_ambulatorial": "1", "atendimento_hospitalar": "0", "urgencia_emergencia": "0", "natureza_juridica": "1023", "nome": "PRESIDIO DE JANUARIA MG"}, {"cnes": "7231660", "tp_unid_cod": "22", "tp_unid": "Consultório Isolado", "cnpj": "00008190563670", "cnpj_mantenedora": "00000000000000", "cep": "39480000", "atende_sus": "0", "atendimento_ambulatorial": "1", "atendimento_hospitalar": "0", "urgencia_emergencia": "0", "natureza_juridica": "4000", "nome": "ORALDENTE ANA CLAUDIA CORREA GONZAGA"}, {"cnes": "7235682", "tp_unid_cod": "22", "tp_unid": "Consultório Isolado", "cnpj": "00082285497687", "cnpj_mantenedora": "00000000000000", "cep": "39480000", "atende_sus": "0", "atendimento_ambulatorial": "1", "atendimento_hospitalar": "0", "urgencia_emergencia": "0", "natureza_juridica": "4000", "nome": "ROSALVA PEREIRA DA SILVA"}, {"cnes": "7242697", "tp_unid_cod": "02", "tp_unid": "Centro de Saúde / UBS", "cnpj": "00000000000000", "cnpj_mantenedora": "21461546000110", "cep": "39480000", "atende_sus": "1", "atendimento_ambulatorial": "1", "atendimento_hospitalar": "0", "urgencia_emergencia": "0", "natureza_juridica": "1244", "nome": "CENTRO AVANCADO DE TRATAMENTO E PESQUISA EM LEISHMANIOSE"}, {"cnes": "7293879", "tp_unid_cod": "36", "tp_unid": "Clínica/Centro de Especialidade", "cnpj": "07394657000120", "cnpj_mantenedora": "00000000000000", "cep": "39480000", "atende_sus": "0", "atendimento_ambulatorial": "1", "atendimento_hospitalar": "0", "urgencia_emergencia": "0", "natureza_juridica": "2062", "nome": "CORTEZ E VIANA LTDA ME"}, {"cnes": "7316577", "tp_unid_cod": "36", "tp_unid": "Clínica/Centro de Especialidade", "cnpj": "17922718000138", "cnpj_mantenedora": "00000000000000", "cep": "39480000", "atende_sus": "0", "atendimento_ambulatorial": "1", "atendimento_hospitalar": "0", "urgencia_emergencia": "0", "natureza_juridica": "2062", "nome": "SETIMA CLINICA DE MEDICINA DO TRABALHO LIMITADA ME"}, {"cnes": "7355580", "tp_unid_cod": "36", "tp_unid": "Clínica/Centro de Especialidade", "cnpj": "15799143000182", "cnpj_mantenedora": "00000000000000", "cep": "39480000", "atende_sus": "0", "atendimento_ambulatorial": "1", "atendimento_hospitalar": "0", "urgencia_emergencia": "0", "natureza_juridica": "2062", "nome": "ORALJAN CLINICA ODONTOLOGICA"}, {"cnes": "7396694", "tp_unid_cod": "02", "tp_unid": "Centro de Saúde / UBS", "cnpj": "08358883000118", "cnpj_mantenedora": "00000000000000", "cep": "39480000", "atende_sus": "0", "atendimento_ambulatorial": "1", "atendimento_hospitalar": "0", "urgencia_emergencia": "0", "natureza_juridica": "3999", "nome": "ASSOCIACAO DE PROTECAO E ASSIST AOS CONDENADOS DE JANUARIA"}, {"cnes": "7489579", "tp_unid_cod": "22", "tp_unid": "Consultório Isolado", "cnpj": "00072577835604", "cnpj_mantenedora": "00000000000000", "cep": "39480000", "atende_sus": "0", "atendimento_ambulatorial": "1", "atendimento_hospitalar": "0", "urgencia_emergencia": "0", "natureza_juridica": "4000", "nome": "SONIA ALVES SIQUEIRA"}, {"cnes": "7548508", "tp_unid_cod": "22", "tp_unid": "Consultório Isolado", "cnpj": "00005573932640", "cnpj_mantenedora": "00000000000000", "cep": "39480000", "atende_sus": "0", "atendimento_ambulatorial": "1", "atendimento_hospitalar": "0", "urgencia_emergencia": "0", "natureza_juridica": "4000", "nome": "CORPUS FISIOTERAPIA E ESTETICA KARINE"}, {"cnes": "7559976", "tp_unid_cod": "36", "tp_unid": "Clínica/Centro de Especialidade", "cnpj": "32374511000160", "cnpj_mantenedora": "00000000000000", "cep": "39480000", "atende_sus": "0", "atendimento_ambulatorial": "1", "atendimento_hospitalar": "0", "urgencia_emergencia": "0", "natureza_juridica": "2135", "nome": "ROGERIA RIBEIRO FISIOTERAPIA E PILATES"}, {"cnes": "7569475", "tp_unid_cod": "36", "tp_unid": "Clínica/Centro de Especialidade", "cnpj": "11067738000192", "cnpj_mantenedora": "00000000000000", "cep": "39480000", "atende_sus": "1", "atendimento_ambulatorial": "1", "atendimento_hospitalar": "0", "urgencia_emergencia": "0", "natureza_juridica": "2062", "nome": "IMED INSTITUTO MEDICO"}, {"cnes": "7569491", "tp_unid_cod": "22", "tp_unid": "Consultório Isolado", "cnpj": "00007073988606", "cnpj_mantenedora": "00000000000000", "cep": "39480000", "atende_sus": "0", "atendimento_ambulatorial": "1", "atendimento_hospitalar": "0", "urgencia_emergencia": "0", "natureza_juridica": "4000", "nome": "EMIDIO OLIVEIRA TEIXEIRA"}, {"cnes": "7719078", "tp_unid_cod": "36", "tp_unid": "Clínica/Centro de Especialidade", "cnpj": "02965892000190", "cnpj_mantenedora": "00000000000000", "cep": "39480000", "atende_sus": "0", "atendimento_ambulatorial": "1", "atendimento_hospitalar": "0", "urgencia_emergencia": "0", "natureza_juridica": "2062", "nome": "CLINICA COFIMINAS"}, {"cnes": "7761104", "tp_unid_cod": "36", "tp_unid": "Clínica/Centro de Especialidade", "cnpj": "20487319000109", "cnpj_mantenedora": "00000000000000", "cep": "39480000", "atende_sus": "0", "atendimento_ambulatorial": "1", "atendimento_hospitalar": "0", "urgencia_emergencia": "0", "natureza_juridica": "2062", "nome": "ASSIS AGUIAR CLINICA MEDICA"}, {"cnes": "7786980", "tp_unid_cod": "22", "tp_unid": "Consultório Isolado", "cnpj": "00010590269615", "cnpj_mantenedora": "00000000000000", "cep": "39480000", "atende_sus": "0", "atendimento_ambulatorial": "1", "atendimento_hospitalar": "0", "urgencia_emergencia": "0", "natureza_juridica": "4000", "nome": "DEMETRIO ALVES ARAUJO"}, {"cnes": "7813678", "tp_unid_cod": "36", "tp_unid": "Clínica/Centro de Especialidade", "cnpj": "17343083000203", "cnpj_mantenedora": "00000000000000", "cep": "39480000", "atende_sus": "0", "atendimento_ambulatorial": "1", "atendimento_hospitalar": "0", "urgencia_emergencia": "0", "natureza_juridica": "2135", "nome": "DR ANDERSON F NASCIMENTO GINEGOLOGIA E OBSTETRICIA"}, {"cnes": "7826788", "tp_unid_cod": "36", "tp_unid": "Clínica/Centro de Especialidade", "cnpj": "11294712000187", "cnpj_mantenedora": "00000000000000", "cep": "39480000", "atende_sus": "0", "atendimento_ambulatorial": "1", "atendimento_hospitalar": "0", "urgencia_emergencia": "0", "natureza_juridica": "2062", "nome": "CENTRO INTEGRADO DE SAUDE"}, {"cnes": "7843887", "tp_unid_cod": "36", "tp_unid": "Clínica/Centro de Especialidade", "cnpj": "21132107000163", "cnpj_mantenedora": "00000000000000", "cep": "39480000", "atende_sus": "1", "atendimento_ambulatorial": "1", "atendimento_hospitalar": "0", "urgencia_emergencia": "0", "natureza_juridica": "2240", "nome": "CENTRO ESPECIALIZADO ODONTOLOGICO"}, {"cnes": "7971893", "tp_unid_cod": "36", "tp_unid": "Clínica/Centro de Especialidade", "cnpj": "24677994000143", "cnpj_mantenedora": "00000000000000", "cep": "39480000", "atende_sus": "0", "atendimento_ambulatorial": "1", "atendimento_hospitalar": "0", "urgencia_emergencia": "0", "natureza_juridica": "2062", "nome": "CLINICAS CONSULTAS JA"}, {"cnes": "8019835", "tp_unid_cod": "36", "tp_unid": "Clínica/Centro de Especialidade", "cnpj": "46536943000134", "cnpj_mantenedora": "00000000000000", "cep": "39480000", "atende_sus": "0", "atendimento_ambulatorial": "1", "atendimento_hospitalar": "0", "urgencia_emergencia": "0", "natureza_juridica": "2062", "nome": "PREVINNE OCUPACIONAL"}, {"cnes": "8021716", "tp_unid_cod": "22", "tp_unid": "Consultório Isolado", "cnpj": "58257865000118", "cnpj_mantenedora": "00000000000000", "cep": "39480000", "atende_sus": "0", "atendimento_ambulatorial": "1", "atendimento_hospitalar": "0", "urgencia_emergencia": "0", "natureza_juridica": "2062", "nome": "OTICAS GUEDES DE JANUARIA"}, {"cnes": "8090378", "tp_unid_cod": "22", "tp_unid": "Consultório Isolado", "cnpj": "64195547000172", "cnpj_mantenedora": "00000000000000", "cep": "39480000", "atende_sus": "0", "atendimento_ambulatorial": "1", "atendimento_hospitalar": "0", "urgencia_emergencia": "0", "natureza_juridica": "2062", "nome": "NORMANHA MEDINA SERVICOS MEDICOS LTDA"}, {"cnes": "8128332", "tp_unid_cod": "36", "tp_unid": "Clínica/Centro de Especialidade", "cnpj": "00000000000000", "cnpj_mantenedora": "21461546000110", "cep": "39480000", "atende_sus": "1", "atendimento_ambulatorial": "1", "atendimento_hospitalar": "0", "urgencia_emergencia": "0", "natureza_juridica": "1244", "nome": "CENTRO DE ESPECIALIDADES MEDICAS CEM"}, {"cnes": "9014977", "tp_unid_cod": "36", "tp_unid": "Clínica/Centro de Especialidade", "cnpj": "24178970000140", "cnpj_mantenedora": "00000000000000", "cep": "39480000", "atende_sus": "0", "atendimento_ambulatorial": "1", "atendimento_hospitalar": "0", "urgencia_emergencia": "0", "natureza_juridica": "2062", "nome": "CLINICA SANTA ALICE EIRELI"}, {"cnes": "9108424", "tp_unid_cod": "22", "tp_unid": "Consultório Isolado", "cnpj": "00000435997610", "cnpj_mantenedora": "00000000000000", "cep": "39480000", "atende_sus": "0", "atendimento_ambulatorial": "1", "atendimento_hospitalar": "0", "urgencia_emergencia": "0", "natureza_juridica": "4000", "nome": "CLOVIS DE SOUZA MOURA"}, {"cnes": "9136428", "tp_unid_cod": "36", "tp_unid": "Clínica/Centro de Especialidade", "cnpj": "26774394000129", "cnpj_mantenedora": "00000000000000", "cep": "39480000", "atende_sus": "0", "atendimento_ambulatorial": "1", "atendimento_hospitalar": "0", "urgencia_emergencia": "0", "natureza_juridica": "2062", "nome": "BIO EQUILIBRIO CLINICA DE FISIOTERAPIA"}, {"cnes": "9227172", "tp_unid_cod": "36", "tp_unid": "Clínica/Centro de Especialidade", "cnpj": "08833544000146", "cnpj_mantenedora": "00000000000000", "cep": "39480000", "atende_sus": "0", "atendimento_ambulatorial": "1", "atendimento_hospitalar": "0", "urgencia_emergencia": "0", "natureza_juridica": "2062", "nome": "CLINICA ODONTOLOGICA SORRIR"}, {"cnes": "9228713", "tp_unid_cod": "36", "tp_unid": "Clínica/Centro de Especialidade", "cnpj": "00000000000000", "cnpj_mantenedora": "01289973000155", "cep": "39480000", "atende_sus": "1", "atendimento_ambulatorial": "1", "atendimento_hospitalar": "0", "urgencia_emergencia": "0", "natureza_juridica": "1210", "nome": "CISAMSF"}, {"cnes": "9361642", "tp_unid_cod": "36", "tp_unid": "Clínica/Centro de Especialidade", "cnpj": "15205448000119", "cnpj_mantenedora": "00000000000000", "cep": "39480000", "atende_sus": "0", "atendimento_ambulatorial": "1", "atendimento_hospitalar": "0", "urgencia_emergencia": "0", "natureza_juridica": "2062", "nome": "CLINICA ANA CLARA"}, {"cnes": "9406271", "tp_unid_cod": "02", "tp_unid": "Centro de Saúde / UBS", "cnpj": "00000000000000", "cnpj_mantenedora": "21461546000110", "cep": "39480000", "atende_sus": "1", "atendimento_ambulatorial": "1", "atendimento_hospitalar": "0", "urgencia_emergencia": "0", "natureza_juridica": "1244", "nome": "CENTRO DE REFERENCIA DA ATENCAO PRIMARIA CREAP"}, {"cnes": "9459294", "tp_unid_cod": "22", "tp_unid": "Consultório Isolado", "cnpj": "09003965000102", "cnpj_mantenedora": "00000000000000", "cep": "39480000", "atende_sus": "0", "atendimento_ambulatorial": "1", "atendimento_hospitalar": "0", "urgencia_emergencia": "0", "natureza_juridica": "2062", "nome": "ANDRADA SAUDE"}, {"cnes": "9783717", "tp_unid_cod": "36", "tp_unid": "Clínica/Centro de Especialidade", "cnpj": "32851524000182", "cnpj_mantenedora": "00000000000000", "cep": "39480000", "atende_sus": "1", "atendimento_ambulatorial": "1", "atendimento_hospitalar": "0", "urgencia_emergencia": "0", "natureza_juridica": "2062", "nome": "ORTOPEDIA FROTA EIRELI"}, {"cnes": "9793194", "tp_unid_cod": "22", "tp_unid": "Consultório Isolado", "cnpj": "00030458115827", "cnpj_mantenedora": "00000000000000", "cep": "39480000", "atende_sus": "0", "atendimento_ambulatorial": "1", "atendimento_hospitalar": "0", "urgencia_emergencia": "0", "natureza_juridica": "4000", "nome": "ELANIO PEREIRA DE ALMEIDA"}]}