{"ibge": 3151503, "codufmun": "315150", "fonte": "cnes_st_mg_202603.parquet", "total_no_municipio": 157, "total_relevante_generalista": 131, "por_tipo": {"Consultório Isolado": 95, "Clínica/Centro de Especialidade": 15, "Centro de Saúde / UBS": 12, "Policlínica": 6, "Posto de Saúde": 2, "Hospital Geral": 1}, "estabelecimentos": [{"cnes": "0151548", "tp_unid_cod": "36", "tp_unid": "Clínica/Centro de Especialidade", "cnpj": "24247640000169", "cnpj_mantenedora": "00000000000000", "cep": "37925000", "atende_sus": "1", "atendimento_ambulatorial": "1", "atendimento_hospitalar": "0", "urgencia_emergencia": "0", "natureza_juridica": "2062", "nome": "DR SERVICOS MEDICOS"}, {"cnes": "0265624", "tp_unid_cod": "22", "tp_unid": "Consultório Isolado", "cnpj": "30629670000132", "cnpj_mantenedora": "00000000000000", "cep": "37925000", "atende_sus": "0", "atendimento_ambulatorial": "1", "atendimento_hospitalar": "0", "urgencia_emergencia": "0", "natureza_juridica": "2305", "nome": "DM FERNANDES SERVICOS MEDICOS EIRELI"}, {"cnes": "0455458", "tp_unid_cod": "22", "tp_unid": "Consultório Isolado", "cnpj": "46962073000165", "cnpj_mantenedora": "00000000000000", "cep": "37925000", "atende_sus": "0", "atendimento_ambulatorial": "1", "atendimento_hospitalar": "0", "urgencia_emergencia": "0", "natureza_juridica": "2135", "nome": "JAINE REIS"}, {"cnes": "0512869", "tp_unid_cod": "22", "tp_unid": "Consultório Isolado", "cnpj": "00009704427697", "cnpj_mantenedora": "00000000000000", "cep": "37925000", "atende_sus": "0", "atendimento_ambulatorial": "1", "atendimento_hospitalar": "0", "urgencia_emergencia": "0", "natureza_juridica": "4000", "nome": "DR LARISSA VAZ"}, {"cnes": "0616702", "tp_unid_cod": "36", "tp_unid": "Clínica/Centro de Especialidade", "cnpj": "25533461000150", "cnpj_mantenedora": "00000000000000", "cep": "37925000", "atende_sus": "1", "atendimento_ambulatorial": "1", "atendimento_hospitalar": "0", "urgencia_emergencia": "0", "natureza_juridica": "2062", "nome": "GMS GRUPO MELHOR SAUDE"}, {"cnes": "0797618", "tp_unid_cod": "22", "tp_unid": "Consultório Isolado", "cnpj": "31075464000190", "cnpj_mantenedora": "00000000000000", "cep": "37925000", "atende_sus": "1", "atendimento_ambulatorial": "1", "atendimento_hospitalar": "0", "urgencia_emergencia": "0", "natureza_juridica": "2062", "nome": "RM SERVICOS MEDICOS"}, {"cnes": "0805297", "tp_unid_cod": "22", "tp_unid": "Consultório Isolado", "cnpj": "40973670000109", "cnpj_mantenedora": "00000000000000", "cep": "37925000", "atende_sus": "1", "atendimento_ambulatorial": "1", "atendimento_hospitalar": "0", "urgencia_emergencia": "0", "natureza_juridica": "2135", "nome": "CLINICA DE FONOAUDIOLOGIA MARIA LUZIMAR"}, {"cnes": "0923370", "tp_unid_cod": "22", "tp_unid": "Consultório Isolado", "cnpj": "24831830000129", "cnpj_mantenedora": "00000000000000", "cep": "37925000", "atende_sus": "0", "atendimento_ambulatorial": "1", "atendimento_hospitalar": "0", "urgencia_emergencia": "0", "natureza_juridica": "2062", "nome": "CLINICA TIRADENTES"}, {"cnes": "0994758", "tp_unid_cod": "02", "tp_unid": "Centro de Saúde / UBS", "cnpj": "00000000000000", "cnpj_mantenedora": "16781346000104", "cep": "37925000", "atende_sus": "1", "atendimento_ambulatorial": "1", "atendimento_hospitalar": "0", "urgencia_emergencia": "0", "natureza_juridica": "1244", "nome": "PSF SARAH VITORIA"}, {"cnes": "2147386", "tp_unid_cod": "36", "tp_unid": "Clínica/Centro de Especialidade", "cnpj": "00000000000000", "cnpj_mantenedora": "16781346000104", "cep": "37925000", "atende_sus": "1", "atendimento_ambulatorial": "1", "atendimento_hospitalar": "0", "urgencia_emergencia": "0", "natureza_juridica": "1244", "nome": "CENTRO DE REABILITACAO E HIDROTERAPIA JOSE RODRIGUES DE CAS"}, {"cnes": "2147394", "tp_unid_cod": "02", "tp_unid": "Centro de Saúde / UBS", "cnpj": "00000000000000", "cnpj_mantenedora": "16781346000104", "cep": "37925000", "atende_sus": "1", "atendimento_ambulatorial": "1", "atendimento_hospitalar": "0", "urgencia_emergencia": "0", "natureza_juridica": "1244", "nome": "PSF BOSSUET COSTA PIUMHI"}, {"cnes": "2147491", "tp_unid_cod": "36", "tp_unid": "Clínica/Centro de Especialidade", "cnpj": "00000000000000", "cnpj_mantenedora": "16781346000104", "cep": "37925000", "atende_sus": "1", "atendimento_ambulatorial": "1", "atendimento_hospitalar": "0", "urgencia_emergencia": "0", "natureza_juridica": "1244", "nome": "DIRETORIA DE SAUDE DE PIUMHI"}, {"cnes": "2172887", "tp_unid_cod": "36", "tp_unid": "Clínica/Centro de Especialidade", "cnpj": "00000000000000", "cnpj_mantenedora": "16781346000104", "cep": "37925000", "atende_sus": "1", "atendimento_ambulatorial": "1", "atendimento_hospitalar": "0", "urgencia_emergencia": "0", "natureza_juridica": "1244", "nome": "SERVICO DE DIAGNOSTICO POR IMAGEM E EXAMES LABORATORIAIS"}, {"cnes": "2172917", "tp_unid_cod": "02", "tp_unid": "Centro de Saúde / UBS", "cnpj": "00000000000000", "cnpj_mantenedora": "16781346000104", "cep": "37925000", "atende_sus": "1", "atendimento_ambulatorial": "1", "atendimento_hospitalar": "0", "urgencia_emergencia": "0", "natureza_juridica": "1244", "nome": "PSF JOSE MARTINS DE FARIA"}, {"cnes": "2759152", "tp_unid_cod": "02", "tp_unid": "Centro de Saúde / UBS", "cnpj": "00000000000000", "cnpj_mantenedora": "16781346000104", "cep": "37925000", "atende_sus": "1", "atendimento_ambulatorial": "1", "atendimento_hospitalar": "0", "urgencia_emergencia": "0", "natureza_juridica": "1244", "nome": "CENTRO DE ATENDIMENTO DA MULHER E DA CRIANCA"}, {"cnes": "2764881", "tp_unid_cod": "22", "tp_unid": "Consultório Isolado", "cnpj": "00068105584620", "cnpj_mantenedora": "00000000000000", "cep": "37925000", "atende_sus": "0", "atendimento_ambulatorial": "1", "atendimento_hospitalar": "0", "urgencia_emergencia": "0", "natureza_juridica": "4000", "nome": "ANGELO GUALBERTO DE MACEDO"}, {"cnes": "2765241", "tp_unid_cod": "22", "tp_unid": "Consultório Isolado", "cnpj": "00038190397672", "cnpj_mantenedora": "00000000000000", "cep": "37925000", "atende_sus": "0", "atendimento_ambulatorial": "1", "atendimento_hospitalar": "0", "urgencia_emergencia": "0", "natureza_juridica": "4000", "nome": "ADIR BATISTA"}, {"cnes": "2775468", "tp_unid_cod": "02", "tp_unid": "Centro de Saúde / UBS", "cnpj": "00000000000000", "cnpj_mantenedora": "16781346000104", "cep": "37925000", "atende_sus": "1", "atendimento_ambulatorial": "1", "atendimento_hospitalar": "0", "urgencia_emergencia": "0", "natureza_juridica": "1244", "nome": "PSF JOAQUIM TERRA DOS SANTOS"}, {"cnes": "2775530", "tp_unid_cod": "02", "tp_unid": "Centro de Saúde / UBS", "cnpj": "00000000000000", "cnpj_mantenedora": "16781346000104", "cep": "37925000", "atende_sus": "1", "atendimento_ambulatorial": "1", "atendimento_hospitalar": "0", "urgencia_emergencia": "0", "natureza_juridica": "1244", "nome": "PSF MARIA REZENDE OLIVEIRA PIUMHI"}, {"cnes": "2775751", "tp_unid_cod": "02", "tp_unid": "Centro de Saúde / UBS", "cnpj": "00000000000000", "cnpj_mantenedora": "16781346000104", "cep": "37925000", "atende_sus": "1", "atendimento_ambulatorial": "1", "atendimento_hospitalar": "0", "urgencia_emergencia": "0", "natureza_juridica": "1244", "nome": "PSF SUDARIO DOS SANTOS"}, {"cnes": "2775786", "tp_unid_cod": "02", "tp_unid": "Centro de Saúde / UBS", "cnpj": "00000000000000", "cnpj_mantenedora": "16781346000104", "cep": "37925000", "atende_sus": "1", "atendimento_ambulatorial": "1", "atendimento_hospitalar": "0", "urgencia_emergencia": "0", "natureza_juridica": "1244", "nome": "UBS AMPLIADA TOTONHA TOME E DONA TINA"}, {"cnes": "2776006", "tp_unid_cod": "05", "tp_unid": "Hospital Geral", "cnpj": "23591126000183", "cnpj_mantenedora": "00000000000000", "cep": "37925000", "atende_sus": "1", "atendimento_ambulatorial": "1", "atendimento_hospitalar": "1", "urgencia_emergencia": "1", "natureza_juridica": "3999", "nome": "SANTA CASA DE MISERICORDIA DE PIUMHI"}, {"cnes": "2837323", "tp_unid_cod": "22", "tp_unid": "Consultório Isolado", "cnpj": "48807489000134", "cnpj_mantenedora": "00000000000000", "cep": "37925000", "atende_sus": "0", "atendimento_ambulatorial": "1", "atendimento_hospitalar": "0", "urgencia_emergencia": "0", "natureza_juridica": "2240", "nome": "DR SAULO ROSA FERREIRA PSIQUIATRA"}, {"cnes": "2861070", "tp_unid_cod": "22", "tp_unid": "Consultório Isolado", "cnpj": "00082635935734", "cnpj_mantenedora": "00000000000000", "cep": "37925000", "atende_sus": "0", "atendimento_ambulatorial": "1", "atendimento_hospitalar": "0", "urgencia_emergencia": "0", "natureza_juridica": "4000", "nome": "CLINICA DE PSIQUIATRIA DR CARLOS FERNANDES BARROS"}, {"cnes": "2886782", "tp_unid_cod": "22", "tp_unid": "Consultório Isolado", "cnpj": "31030320000118", "cnpj_mantenedora": "00000000000000", "cep": "37925000", "atende_sus": "1", "atendimento_ambulatorial": "1", "atendimento_hospitalar": "0", "urgencia_emergencia": "0", "natureza_juridica": "2135", "nome": "CLINICA SAO JUDAS TADEU"}, {"cnes": "2999323", "tp_unid_cod": "22", "tp_unid": "Consultório Isolado", "cnpj": "38242808000239", "cnpj_mantenedora": "00000000000000", "cep": "37925000", "atende_sus": "1", "atendimento_ambulatorial": "1", "atendimento_hospitalar": "0", "urgencia_emergencia": "0", "natureza_juridica": "2062", "nome": "ERGOSEG"}, {"cnes": "3164608", "tp_unid_cod": "22", "tp_unid": "Consultório Isolado", "cnpj": "04490201000175", "cnpj_mantenedora": "00000000000000", "cep": "37925000", "atende_sus": "0", "atendimento_ambulatorial": "1", "atendimento_hospitalar": "0", "urgencia_emergencia": "0", "natureza_juridica": "2240", "nome": "RECUPERARTE CLINICA DE FISIOTERAPIA LTDA"}, {"cnes": "3243893", "tp_unid_cod": "02", "tp_unid": "Centro de Saúde / UBS", "cnpj": "00000000000000", "cnpj_mantenedora": "16781346000104", "cep": "37925000", "atende_sus": "1", "atendimento_ambulatorial": "1", "atendimento_hospitalar": "0", "urgencia_emergencia": "0", "natureza_juridica": "1244", "nome": "UNIDADE BASICA DE SAUDE AMPLIADA JOAO GUILHERME TO E RURAL"}, {"cnes": "3243907", "tp_unid_cod": "02", "tp_unid": "Centro de Saúde / UBS", "cnpj": "00000000000000", "cnpj_mantenedora": "16781346000104", "cep": "37925000", "atende_sus": "1", "atendimento_ambulatorial": "1", "atendimento_hospitalar": "0", "urgencia_emergencia": "0", "natureza_juridica": "1244", "nome": "PSF INHO FIRMINO"}, {"cnes": "3503852", "tp_unid_cod": "22", "tp_unid": "Consultório Isolado", "cnpj": "00000360217680", "cnpj_mantenedora": "00000000000000", "cep": "37925000", "atende_sus": "0", "atendimento_ambulatorial": "1", "atendimento_hospitalar": "0", "urgencia_emergencia": "0", "natureza_juridica": "4000", "nome": "WANESSA DORNELA DE OLIVEIRA"}, {"cnes": "3503860", "tp_unid_cod": "22", "tp_unid": "Consultório Isolado", "cnpj": "00011906251649", "cnpj_mantenedora": "00000000000000", "cep": "37925000", "atende_sus": "0", "atendimento_ambulatorial": "1", "atendimento_hospitalar": "0", "urgencia_emergencia": "0", "natureza_juridica": "4000", "nome": "JOSE RUBENS DE MOURA SANTOS"}, {"cnes": "3503879", "tp_unid_cod": "22", "tp_unid": "Consultório Isolado", "cnpj": "00002880993628", "cnpj_mantenedora": "00000000000000", "cep": "37925000", "atende_sus": "0", "atendimento_ambulatorial": "1", "atendimento_hospitalar": "0", "urgencia_emergencia": "0", "natureza_juridica": "4000", "nome": "MEDICINA DA CRIANCA E DO ADOLESCENTE"}, {"cnes": "3684334", "tp_unid_cod": "22", "tp_unid": "Consultório Isolado", "cnpj": "00020326190678", "cnpj_mantenedora": "00000000000000", "cep": "37925000", "atende_sus": "0", "atendimento_ambulatorial": "1", "atendimento_hospitalar": "0", "urgencia_emergencia": "0", "natureza_juridica": "4000", "nome": "ANTONIO CARLOS DE FARIA"}, {"cnes": "3684350", "tp_unid_cod": "36", "tp_unid": "Clínica/Centro de Especialidade", "cnpj": "20939328000185", "cnpj_mantenedora": "00000000000000", "cep": "37925000", "atende_sus": "1", "atendimento_ambulatorial": "1", "atendimento_hospitalar": "0", "urgencia_emergencia": "0", "natureza_juridica": "3999", "nome": "APAE DE PIUMHI"}, {"cnes": "3684458", "tp_unid_cod": "22", "tp_unid": "Consultório Isolado", "cnpj": "07589277000140", "cnpj_mantenedora": "00000000000000", "cep": "37925000", "atende_sus": "0", "atendimento_ambulatorial": "1", "atendimento_hospitalar": "0", "urgencia_emergencia": "0", "natureza_juridica": "2240", "nome": "FISIOCENTER"}, {"cnes": "3684490", "tp_unid_cod": "22", "tp_unid": "Consultório Isolado", "cnpj": "00014128276634", "cnpj_mantenedora": "00000000000000", "cep": "37925000", "atende_sus": "0", "atendimento_ambulatorial": "1", "atendimento_hospitalar": "0", "urgencia_emergencia": "0", "natureza_juridica": "4000", "nome": "EDSON ANTONIO JULIO"}, {"cnes": "3684547", "tp_unid_cod": "22", "tp_unid": "Consultório Isolado", "cnpj": "00071267522615", "cnpj_mantenedora": "00000000000000", "cep": "37925000", "atende_sus": "0", "atendimento_ambulatorial": "1", "atendimento_hospitalar": "0", "urgencia_emergencia": "0", "natureza_juridica": "4000", "nome": "HERALDO FRANCISCO COSTA"}, {"cnes": "3684563", "tp_unid_cod": "22", "tp_unid": "Consultório Isolado", "cnpj": "00000883247615", "cnpj_mantenedora": "00000000000000", "cep": "37925000", "atende_sus": "0", "atendimento_ambulatorial": "1", "atendimento_hospitalar": "0", "urgencia_emergencia": "0", "natureza_juridica": "4000", "nome": "ITAMAR LOPES DA CUNHA"}, {"cnes": "3684601", "tp_unid_cod": "22", "tp_unid": "Consultório Isolado", "cnpj": "00006995500687", "cnpj_mantenedora": "00000000000000", "cep": "37925000", "atende_sus": "0", "atendimento_ambulatorial": "1", "atendimento_hospitalar": "0", "urgencia_emergencia": "0", "natureza_juridica": "4000", "nome": "IVO DE ANDRADE"}, {"cnes": "3685136", "tp_unid_cod": "22", "tp_unid": "Consultório Isolado", "cnpj": "00028803213600", "cnpj_mantenedora": "00000000000000", "cep": "37925000", "atende_sus": "0", "atendimento_ambulatorial": "1", "atendimento_hospitalar": "0", "urgencia_emergencia": "0", "natureza_juridica": "4000", "nome": "JOAO DE OLIVEIRA TERRA JUNIOR"}, {"cnes": "3685160", "tp_unid_cod": "22", "tp_unid": "Consultório Isolado", "cnpj": "00020921969600", "cnpj_mantenedora": "00000000000000", "cep": "37925000", "atende_sus": "0", "atendimento_ambulatorial": "1", "atendimento_hospitalar": "0", "urgencia_emergencia": "0", "natureza_juridica": "4000", "nome": "NUCLEO DERMATOLOGICO CIRURGICO"}, {"cnes": "3685217", "tp_unid_cod": "04", "tp_unid": "Policlínica", "cnpj": "50164727000182", "cnpj_mantenedora": "00000000000000", "cep": "37925000", "atende_sus": "0", "atendimento_ambulatorial": "1", "atendimento_hospitalar": "0", "urgencia_emergencia": "0", "natureza_juridica": "2062", "nome": "CONSULTORIO MEDICO DR LUIS AUGUSTO RODRIGUES LTDA"}, {"cnes": "3685225", "tp_unid_cod": "22", "tp_unid": "Consultório Isolado", "cnpj": "00089934997649", "cnpj_mantenedora": "00000000000000", "cep": "37925000", "atende_sus": "0", "atendimento_ambulatorial": "1", "atendimento_hospitalar": "0", "urgencia_emergencia": "0", "natureza_juridica": "4000", "nome": "MARCELO MESSIAS LOPES"}, {"cnes": "3685241", "tp_unid_cod": "22", "tp_unid": "Consultório Isolado", "cnpj": "00051071517600", "cnpj_mantenedora": "00000000000000", "cep": "37925000", "atende_sus": "0", "atendimento_ambulatorial": "1", "atendimento_hospitalar": "0", "urgencia_emergencia": "0", "natureza_juridica": "4000", "nome": "SOLANGE BARCELOS COSTA GATTI"}, {"cnes": "3685284", "tp_unid_cod": "04", "tp_unid": "Policlínica", "cnpj": "18912894000151", "cnpj_mantenedora": "00000000000000", "cep": "37925000", "atende_sus": "0", "atendimento_ambulatorial": "1", "atendimento_hospitalar": "0", "urgencia_emergencia": "0", "natureza_juridica": "2062", "nome": "CLINICA DR WESLEY DA COSTA MOTA FILHOS LTDA"}, {"cnes": "4053346", "tp_unid_cod": "22", "tp_unid": "Consultório Isolado", "cnpj": "48217505000139", "cnpj_mantenedora": "00000000000000", "cep": "37925000", "atende_sus": "0", "atendimento_ambulatorial": "1", "atendimento_hospitalar": "0", "urgencia_emergencia": "0", "natureza_juridica": "2062", "nome": "CLINICA AME"}, {"cnes": "4111869", "tp_unid_cod": "22", "tp_unid": "Consultório Isolado", "cnpj": "37440360000114", "cnpj_mantenedora": "00000000000000", "cep": "37925000", "atende_sus": "0", "atendimento_ambulatorial": "1", "atendimento_hospitalar": "0", "urgencia_emergencia": "0", "natureza_juridica": "2062", "nome": "ML SERVICOS MEDICOS ASSOCIADOS LTDA"}, {"cnes": "4230833", "tp_unid_cod": "22", "tp_unid": "Consultório Isolado", "cnpj": "23591290000190", "cnpj_mantenedora": "00000000000000", "cep": "37925000", "atende_sus": "0", "atendimento_ambulatorial": "1", "atendimento_hospitalar": "0", "urgencia_emergencia": "0", "natureza_juridica": "3999", "nome": "SOCIEDADE DE SAO VICENTE DE PAULO DE PIUMHI"}, {"cnes": "4364813", "tp_unid_cod": "04", "tp_unid": "Policlínica", "cnpj": "27854224000117", "cnpj_mantenedora": "00000000000000", "cep": "37925000", "atende_sus": "0", "atendimento_ambulatorial": "1", "atendimento_hospitalar": "0", "urgencia_emergencia": "0", "natureza_juridica": "2135", "nome": "PAULO DOS REIS JARDIM"}, {"cnes": "4475100", "tp_unid_cod": "22", "tp_unid": "Consultório Isolado", "cnpj": "20547651000103", "cnpj_mantenedora": "00000000000000", "cep": "37925000", "atende_sus": "0", "atendimento_ambulatorial": "1", "atendimento_hospitalar": "0", "urgencia_emergencia": "0", "natureza_juridica": "2240", "nome": "CLINICA PSICOLOGICA GONCALVES LTDA"}, {"cnes": "4515560", "tp_unid_cod": "36", "tp_unid": "Clínica/Centro de Especialidade", "cnpj": "00000000000000", "cnpj_mantenedora": "16781346000104", "cep": "37925000", "atende_sus": "1", "atendimento_ambulatorial": "1", "atendimento_hospitalar": "0", "urgencia_emergencia": "0", "natureza_juridica": "1244", "nome": "CENTRO DE FISIOTERAPIA RESPIRATORIA ITAMAR SANTINHO"}, {"cnes": "4521773", "tp_unid_cod": "22", "tp_unid": "Consultório Isolado", "cnpj": "00051071533649", "cnpj_mantenedora": "00000000000000", "cep": "37925000", "atende_sus": "0", "atendimento_ambulatorial": "1", "atendimento_hospitalar": "0", "urgencia_emergencia": "0", "natureza_juridica": "4000", "nome": "ALDO JOSE COSTA"}, {"cnes": "4730275", "tp_unid_cod": "22", "tp_unid": "Consultório Isolado", "cnpj": "00007904099683", "cnpj_mantenedora": "00000000000000", "cep": "37925000", "atende_sus": "0", "atendimento_ambulatorial": "1", "atendimento_hospitalar": "0", "urgencia_emergencia": "0", "natureza_juridica": "4000", "nome": "GIL CESAR PAIVA"}, {"cnes": "4816366", "tp_unid_cod": "02", "tp_unid": "Centro de Saúde / UBS", "cnpj": "00000000000000", "cnpj_mantenedora": "16781346000104", "cep": "37925000", "atende_sus": "1", "atendimento_ambulatorial": "1", "atendimento_hospitalar": "0", "urgencia_emergencia": "0", "natureza_juridica": "1244", "nome": "PSF JOAQUIM TOME DE ANDRADE"}, {"cnes": "4826604", "tp_unid_cod": "04", "tp_unid": "Policlínica", "cnpj": "54273979000109", "cnpj_mantenedora": "00000000000000", "cep": "37925000", "atende_sus": "0", "atendimento_ambulatorial": "1", "atendimento_hospitalar": "0", "urgencia_emergencia": "0", "natureza_juridica": "2062", "nome": "INSTITUTO ACOLHER TERAPIAS INTEGRADAS"}, {"cnes": "4893859", "tp_unid_cod": "22", "tp_unid": "Consultório Isolado", "cnpj": "32320268000105", "cnpj_mantenedora": "00000000000000", "cep": "37925000", "atende_sus": "0", "atendimento_ambulatorial": "1", "atendimento_hospitalar": "0", "urgencia_emergencia": "0", "natureza_juridica": "2062", "nome": "CLINICA DR EDUARDO BELIZARIO XAVIER"}, {"cnes": "4908856", "tp_unid_cod": "22", "tp_unid": "Consultório Isolado", "cnpj": "00010606058648", "cnpj_mantenedora": "00000000000000", "cep": "37925000", "atende_sus": "0", "atendimento_ambulatorial": "1", "atendimento_hospitalar": "0", "urgencia_emergencia": "0", "natureza_juridica": "4000", "nome": "BRUNA LOPES FISIOTERAPIA E PILATES"}, {"cnes": "4908872", "tp_unid_cod": "22", "tp_unid": "Consultório Isolado", "cnpj": "40733262000180", "cnpj_mantenedora": "00000000000000", "cep": "37925000", "atende_sus": "0", "atendimento_ambulatorial": "1", "atendimento_hospitalar": "0", "urgencia_emergencia": "0", "natureza_juridica": "2135", "nome": "MARIA FIEIRA DE FARIA"}, {"cnes": "4910273", "tp_unid_cod": "22", "tp_unid": "Consultório Isolado", "cnpj": "57785192000106", "cnpj_mantenedora": "00000000000000", "cep": "37925000", "atende_sus": "0", "atendimento_ambulatorial": "1", "atendimento_hospitalar": "0", "urgencia_emergencia": "0", "natureza_juridica": "2062", "nome": "SORRIR ODONTOLOGIA PIUMHI LTDA"}, {"cnes": "4945557", "tp_unid_cod": "36", "tp_unid": "Clínica/Centro de Especialidade", "cnpj": "55457339000103", "cnpj_mantenedora": "00000000000000", "cep": "37925000", "atende_sus": "0", "atendimento_ambulatorial": "1", "atendimento_hospitalar": "0", "urgencia_emergencia": "0", "natureza_juridica": "2062", "nome": "BORBOLETANDO CLINICA MULTIDISCIPLINAR DE REABILITACAO"}, {"cnes": "4945824", "tp_unid_cod": "22", "tp_unid": "Consultório Isolado", "cnpj": "00007675782607", "cnpj_mantenedora": "00000000000000", "cep": "37925000", "atende_sus": "0", "atendimento_ambulatorial": "1", "atendimento_hospitalar": "0", "urgencia_emergencia": "0", "natureza_juridica": "4000", "nome": "SAWBONA TERAPIAS INTEGRATIVAS"}, {"cnes": "4963148", "tp_unid_cod": "36", "tp_unid": "Clínica/Centro de Especialidade", "cnpj": "00000000000000", "cnpj_mantenedora": "16781346000104", "cep": "37925000", "atende_sus": "1", "atendimento_ambulatorial": "1", "atendimento_hospitalar": "0", "urgencia_emergencia": "0", "natureza_juridica": "1244", "nome": "ESPACO DA INCLUSAO"}, {"cnes": "4999002", "tp_unid_cod": "22", "tp_unid": "Consultório Isolado", "cnpj": "55882959000190", "cnpj_mantenedora": "00000000000000", "cep": "37925000", "atende_sus": "0", "atendimento_ambulatorial": "1", "atendimento_hospitalar": "0", "urgencia_emergencia": "0", "natureza_juridica": "2062", "nome": "AME KIDS LTDA"}, {"cnes": "4999010", "tp_unid_cod": "22", "tp_unid": "Consultório Isolado", "cnpj": "55860517000142", "cnpj_mantenedora": "00000000000000", "cep": "37925000", "atende_sus": "0", "atendimento_ambulatorial": "1", "atendimento_hospitalar": "0", "urgencia_emergencia": "0", "natureza_juridica": "2062", "nome": "SUPERA LTDA"}, {"cnes": "4999029", "tp_unid_cod": "22", "tp_unid": "Consultório Isolado", "cnpj": "55805372000187", "cnpj_mantenedora": "00000000000000", "cep": "37925000", "atende_sus": "0", "atendimento_ambulatorial": "1", "atendimento_hospitalar": "0", "urgencia_emergencia": "0", "natureza_juridica": "2062", "nome": "FW FONOAUDIOLOGIA ESPECIALIZADA LTDA"}, {"cnes": "5000025", "tp_unid_cod": "22", "tp_unid": "Consultório Isolado", "cnpj": "17747812000106", "cnpj_mantenedora": "00000000000000", "cep": "37925000", "atende_sus": "1", "atendimento_ambulatorial": "1", "atendimento_hospitalar": "0", "urgencia_emergencia": "0", "natureza_juridica": "2240", "nome": "CENTRO MEDICO CSW SAUDE ME"}, {"cnes": "5174317", "tp_unid_cod": "22", "tp_unid": "Consultório Isolado", "cnpj": "00019983093634", "cnpj_mantenedora": "00000000000000", "cep": "37925000", "atende_sus": "0", "atendimento_ambulatorial": "1", "atendimento_hospitalar": "0", "urgencia_emergencia": "0", "natureza_juridica": "4000", "nome": "NELSON SOARES DE MELO"}, {"cnes": "5256682", "tp_unid_cod": "22", "tp_unid": "Consultório Isolado", "cnpj": "02980717000253", "cnpj_mantenedora": "00000000000000", "cep": "37925000", "atende_sus": "0", "atendimento_ambulatorial": "1", "atendimento_hospitalar": "0", "urgencia_emergencia": "0", "natureza_juridica": "2062", "nome": "CLINICA DR ROBERTO H HIROTA"}, {"cnes": "5256739", "tp_unid_cod": "22", "tp_unid": "Consultório Isolado", "cnpj": "00003611224626", "cnpj_mantenedora": "00000000000000", "cep": "37925000", "atende_sus": "0", "atendimento_ambulatorial": "1", "atendimento_hospitalar": "0", "urgencia_emergencia": "0", "natureza_juridica": "4000", "nome": "ELISANGELA MARCIA DE OLIVEIRA"}, {"cnes": "5268516", "tp_unid_cod": "22", "tp_unid": "Consultório Isolado", "cnpj": "30960528000173", "cnpj_mantenedora": "00000000000000", "cep": "37925000", "atende_sus": "1", "atendimento_ambulatorial": "1", "atendimento_hospitalar": "0", "urgencia_emergencia": "0", "natureza_juridica": "2062", "nome": "PEDHOF SERVICOS MEDICOS"}, {"cnes": "5404584", "tp_unid_cod": "22", "tp_unid": "Consultório Isolado", "cnpj": "59428263000149", "cnpj_mantenedora": "00000000000000", "cep": "37925000", "atende_sus": "0", "atendimento_ambulatorial": "1", "atendimento_hospitalar": "0", "urgencia_emergencia": "0", "natureza_juridica": "2062", "nome": "CLINICA PSICOLOGICA DRA KELY CRISTINA DO PRADO LTDA"}, {"cnes": "5454220", "tp_unid_cod": "22", "tp_unid": "Consultório Isolado", "cnpj": "19038494000121", "cnpj_mantenedora": "00000000000000", "cep": "37925000", "atende_sus": "1", "atendimento_ambulatorial": "1", "atendimento_hospitalar": "0", "urgencia_emergencia": "0", "natureza_juridica": "2062", "nome": "JACAL SERVICOS MEDICOS LTDA"}, {"cnes": "5544793", "tp_unid_cod": "22", "tp_unid": "Consultório Isolado", "cnpj": "54966123000100", "cnpj_mantenedora": "00000000000000", "cep": "37925000", "atende_sus": "1", "atendimento_ambulatorial": "1", "atendimento_hospitalar": "0", "urgencia_emergencia": "0", "natureza_juridica": "2135", "nome": "AECIO XAVIER SILVA"}, {"cnes": "5553245", "tp_unid_cod": "22", "tp_unid": "Consultório Isolado", "cnpj": "28999072000103", "cnpj_mantenedora": "00000000000000", "cep": "37925000", "atende_sus": "1", "atendimento_ambulatorial": "1", "atendimento_hospitalar": "0", "urgencia_emergencia": "0", "natureza_juridica": "2062", "nome": "FALCUCCI ATIVIDADES MEDICAS LTDA"}, {"cnes": "5555051", "tp_unid_cod": "22", "tp_unid": "Consultório Isolado", "cnpj": "19335419000122", "cnpj_mantenedora": "00000000000000", "cep": "37925000", "atende_sus": "1", "atendimento_ambulatorial": "1", "atendimento_hospitalar": "0", "urgencia_emergencia": "0", "natureza_juridica": "2062", "nome": "ANDRE LUIS SANTOS CASTRO LTDA"}, {"cnes": "5573963", "tp_unid_cod": "22", "tp_unid": "Consultório Isolado", "cnpj": "21152919000170", "cnpj_mantenedora": "00000000000000", "cep": "37925000", "atende_sus": "1", "atendimento_ambulatorial": "1", "atendimento_hospitalar": "0", "urgencia_emergencia": "0", "natureza_juridica": "2062", "nome": "CLINICA MEDICA E ODONTOLOGICA DR DIEGO MOTA CIA LTDA"}, {"cnes": "5681049", "tp_unid_cod": "04", "tp_unid": "Policlínica", "cnpj": "60862488000198", "cnpj_mantenedora": "00000000000000", "cep": "37925000", "atende_sus": "0", "atendimento_ambulatorial": "1", "atendimento_hospitalar": "0", "urgencia_emergencia": "0", "natureza_juridica": "2062", "nome": "SHR TERAPIA OCUPACIONAL LTDA"}, {"cnes": "5851335", "tp_unid_cod": "22", "tp_unid": "Consultório Isolado", "cnpj": "00051502496100", "cnpj_mantenedora": "00000000000000", "cep": "37925000", "atende_sus": "0", "atendimento_ambulatorial": "1", "atendimento_hospitalar": "0", "urgencia_emergencia": "0", "natureza_juridica": "4000", "nome": "ANDERSEN TERRA DE OLIVEIRA"}, {"cnes": "5944058", "tp_unid_cod": "22", "tp_unid": "Consultório Isolado", "cnpj": "54058401000121", "cnpj_mantenedora": "00000000000000", "cep": "37925000", "atende_sus": "0", "atendimento_ambulatorial": "1", "atendimento_hospitalar": "0", "urgencia_emergencia": "0", "natureza_juridica": "2062", "nome": "PRIORIZZE"}, {"cnes": "5992052", "tp_unid_cod": "22", "tp_unid": "Consultório Isolado", "cnpj": "44653795000102", "cnpj_mantenedora": "00000000000000", "cep": "37925000", "atende_sus": "0", "atendimento_ambulatorial": "1", "atendimento_hospitalar": "0", "urgencia_emergencia": "0", "natureza_juridica": "2062", "nome": "SBS SAUDE LTDA"}, {"cnes": "6122779", "tp_unid_cod": "22", "tp_unid": "Consultório Isolado", "cnpj": "00000241238625", "cnpj_mantenedora": "00000000000000", "cep": "37925000", "atende_sus": "0", "atendimento_ambulatorial": "1", "atendimento_hospitalar": "0", "urgencia_emergencia": "0", "natureza_juridica": "4000", "nome": "FABIANA DE ANDRADE MOURA"}, {"cnes": "6146813", "tp_unid_cod": "36", "tp_unid": "Clínica/Centro de Especialidade", "cnpj": "00000000000000", "cnpj_mantenedora": "16781346000104", "cep": "37925000", "atende_sus": "1", "atendimento_ambulatorial": "1", "atendimento_hospitalar": "0", "urgencia_emergencia": "0", "natureza_juridica": "1244", "nome": "CENTRO DE ESPEC ODONT SOCRATES ALVES DA COSTA"}, {"cnes": "6235077", "tp_unid_cod": "22", "tp_unid": "Consultório Isolado", "cnpj": "10705456000100", "cnpj_mantenedora": "00000000000000", "cep": "37925000", "atende_sus": "0", "atendimento_ambulatorial": "1", "atendimento_hospitalar": "0", "urgencia_emergencia": "0", "natureza_juridica": "2062", "nome": "CLINICA DE IMAGEM PIUMHI LTDA"}, {"cnes": "6313205", "tp_unid_cod": "22", "tp_unid": "Consultório Isolado", "cnpj": "00065834011691", "cnpj_mantenedora": "00000000000000", "cep": "37925000", "atende_sus": "1", "atendimento_ambulatorial": "1", "atendimento_hospitalar": "0", "urgencia_emergencia": "0", "natureza_juridica": "4000", "nome": "MARIA APARECIDA VELOSO SOARES LIMA"}, {"cnes": "6313388", "tp_unid_cod": "22", "tp_unid": "Consultório Isolado", "cnpj": "00096902876649", "cnpj_mantenedora": "00000000000000", "cep": "37925000", "atende_sus": "0", "atendimento_ambulatorial": "1", "atendimento_hospitalar": "0", "urgencia_emergencia": "0", "natureza_juridica": "4000", "nome": "MOYSA CRISTINA NOVAES"}, {"cnes": "6347606", "tp_unid_cod": "04", "tp_unid": "Policlínica", "cnpj": "00950791000110", "cnpj_mantenedora": "00000000000000", "cep": "37925000", "atende_sus": "0", "atendimento_ambulatorial": "1", "atendimento_hospitalar": "0", "urgencia_emergencia": "0", "natureza_juridica": "2062", "nome": "CASA DE SAUDE SAO RAFAEL"}, {"cnes": "6437567", "tp_unid_cod": "22", "tp_unid": "Consultório Isolado", "cnpj": "00003557048624", "cnpj_mantenedora": "00000000000000", "cep": "37925000", "atende_sus": "0", "atendimento_ambulatorial": "1", "atendimento_hospitalar": "0", "urgencia_emergencia": "0", "natureza_juridica": "4000", "nome": "TALITA SANTOS FARIA"}, {"cnes": "6460674", "tp_unid_cod": "22", "tp_unid": "Consultório Isolado", "cnpj": "10572612000102", "cnpj_mantenedora": "00000000000000", "cep": "37925000", "atende_sus": "1", "atendimento_ambulatorial": "1", "atendimento_hospitalar": "0", "urgencia_emergencia": "0", "natureza_juridica": "2240", "nome": "MR SERVICOS MEDICOS LTDA"}, {"cnes": "6466508", "tp_unid_cod": "22", "tp_unid": "Consultório Isolado", "cnpj": "00095646175615", "cnpj_mantenedora": "00000000000000", "cep": "37925000", "atende_sus": "0", "atendimento_ambulatorial": "1", "atendimento_hospitalar": "0", "urgencia_emergencia": "0", "natureza_juridica": "4000", "nome": "VITAL CENTRO"}, {"cnes": "6705375", "tp_unid_cod": "36", "tp_unid": "Clínica/Centro de Especialidade", "cnpj": "00000000000000", "cnpj_mantenedora": "01197487000107", "cep": "37925000", "atende_sus": "1", "atendimento_ambulatorial": "1", "atendimento_hospitalar": "0", "urgencia_emergencia": "0", "natureza_juridica": "1210", "nome": "CONSORCIO INTERMUNICIPAL DE SAUDE CINSC"}, {"cnes": "6707084", "tp_unid_cod": "22", "tp_unid": "Consultório Isolado", "cnpj": "00002549350600", "cnpj_mantenedora": "00000000000000", "cep": "37925000", "atende_sus": "0", "atendimento_ambulatorial": "1", "atendimento_hospitalar": "0", "urgencia_emergencia": "0", "natureza_juridica": "4000", "nome": "ELAINE APARECIDA SANTOS SILVA"}, {"cnes": "6735673", "tp_unid_cod": "22", "tp_unid": "Consultório Isolado", "cnpj": "00002754211632", "cnpj_mantenedora": "00000000000000", "cep": "37925000", "atende_sus": "0", "atendimento_ambulatorial": "1", "atendimento_hospitalar": "0", "urgencia_emergencia": "0", "natureza_juridica": "4000", "nome": "ADRIANA CORREA DINIZ"}, {"cnes": "6915612", "tp_unid_cod": "22", "tp_unid": "Consultório Isolado", "cnpj": "00096073900678", "cnpj_mantenedora": "00000000000000", "cep": "37925000", "atende_sus": "0", "atendimento_ambulatorial": "1", "atendimento_hospitalar": "0", "urgencia_emergencia": "0", "natureza_juridica": "4000", "nome": "HILDEBRANDO ROSA JUNIOR"}, {"cnes": "7065825", "tp_unid_cod": "22", "tp_unid": "Consultório Isolado", "cnpj": "05728521000183", "cnpj_mantenedora": "00000000000000", "cep": "37925000", "atende_sus": "0", "atendimento_ambulatorial": "1", "atendimento_hospitalar": "0", "urgencia_emergencia": "0", "natureza_juridica": "3999", "nome": "CASA DE MARIA"}, {"cnes": "7095112", "tp_unid_cod": "22", "tp_unid": "Consultório Isolado", "cnpj": "00005206659614", "cnpj_mantenedora": "00000000000000", "cep": "37925000", "atende_sus": "0", "atendimento_ambulatorial": "1", "atendimento_hospitalar": "0", "urgencia_emergencia": "0", "natureza_juridica": "4000", "nome": "CONSULTORIO DE PSICOLOGIA"}, {"cnes": "7162545", "tp_unid_cod": "22", "tp_unid": "Consultório Isolado", "cnpj": "41931445000334", "cnpj_mantenedora": "00000000000000", "cep": "37925000", "atende_sus": "0", "atendimento_ambulatorial": "1", "atendimento_hospitalar": "0", "urgencia_emergencia": "0", "natureza_juridica": "2143", "nome": "CONSULTORIO ODONTOLOGICO SICCOB CREDIFOR"}, {"cnes": "7165900", "tp_unid_cod": "36", "tp_unid": "Clínica/Centro de Especialidade", "cnpj": "15019049000163", "cnpj_mantenedora": "00000000000000", "cep": "37925000", "atende_sus": "1", "atendimento_ambulatorial": "1", "atendimento_hospitalar": "0", "urgencia_emergencia": "0", "natureza_juridica": "2240", "nome": "PULMOCARDIO CLINICA DE FISIOTERAPIA LTDA"}, {"cnes": "7332653", "tp_unid_cod": "01", "tp_unid": "Posto de Saúde", "cnpj": "00000000000000", "cnpj_mantenedora": "05487631000109", "cep": "37925000", "atende_sus": "1", "atendimento_ambulatorial": "1", "atendimento_hospitalar": "0", "urgencia_emergencia": "0", "natureza_juridica": "1023", "nome": "PRESIDIO DE PIUMHI MG"}, {"cnes": "7337612", "tp_unid_cod": "22", "tp_unid": "Consultório Isolado", "cnpj": "00002659393648", "cnpj_mantenedora": "00000000000000", "cep": "37925000", "atende_sus": "0", "atendimento_ambulatorial": "1", "atendimento_hospitalar": "0", "urgencia_emergencia": "0", "natureza_juridica": "4000", "nome": "BEM VIVER"}, {"cnes": "7358172", "tp_unid_cod": "22", "tp_unid": "Consultório Isolado", "cnpj": "16716081000160", "cnpj_mantenedora": "00000000000000", "cep": "37925000", "atende_sus": "0", "atendimento_ambulatorial": "1", "atendimento_hospitalar": "0", "urgencia_emergencia": "0", "natureza_juridica": "2062", "nome": "SINAI RESIDENCIAL GERIATRICO"}, {"cnes": "7445016", "tp_unid_cod": "22", "tp_unid": "Consultório Isolado", "cnpj": "00057244995687", "cnpj_mantenedora": "00000000000000", "cep": "37925000", "atende_sus": "0", "atendimento_ambulatorial": "1", "atendimento_hospitalar": "0", "urgencia_emergencia": "0", "natureza_juridica": "4000", "nome": "EULALIA SOARES DA COSTA"}, {"cnes": "7468431", "tp_unid_cod": "22", "tp_unid": "Consultório Isolado", "cnpj": "00068105266687", "cnpj_mantenedora": "00000000000000", "cep": "37925000", "atende_sus": "0", "atendimento_ambulatorial": "1", "atendimento_hospitalar": "0", "urgencia_emergencia": "0", "natureza_juridica": "4000", "nome": "CONSULTORIO ODONTOLOGIO SAINT MARTIN"}, {"cnes": "7474342", "tp_unid_cod": "22", "tp_unid": "Consultório Isolado", "cnpj": "00068105843668", "cnpj_mantenedora": "00000000000000", "cep": "37925000", "atende_sus": "0", "atendimento_ambulatorial": "1", "atendimento_hospitalar": "0", "urgencia_emergencia": "0", "natureza_juridica": "4000", "nome": "CLINICA DE ESTETICA UILSA COSTA LIMA"}, {"cnes": "7938055", "tp_unid_cod": "22", "tp_unid": "Consultório Isolado", "cnpj": "21796470000183", "cnpj_mantenedora": "00000000000000", "cep": "37925000", "atende_sus": "0", "atendimento_ambulatorial": "1", "atendimento_hospitalar": "0", "urgencia_emergencia": "0", "natureza_juridica": "2062", "nome": "RADIOGRAPHI"}, {"cnes": "8011893", "tp_unid_cod": "01", "tp_unid": "Posto de Saúde", "cnpj": "00000000000000", "cnpj_mantenedora": "16781346000104", "cep": "37925000", "atende_sus": "1", "atendimento_ambulatorial": "1", "atendimento_hospitalar": "0", "urgencia_emergencia": "0", "natureza_juridica": "1244", "nome": "PSF MARCINHO CONTADOR"}, {"cnes": "8011915", "tp_unid_cod": "02", "tp_unid": "Centro de Saúde / UBS", "cnpj": "00000000000000", "cnpj_mantenedora": "16781346000104", "cep": "37925000", "atende_sus": "1", "atendimento_ambulatorial": "1", "atendimento_hospitalar": "0", "urgencia_emergencia": "0", "natureza_juridica": "1244", "nome": "PSF MITERMAYER TERRA"}, {"cnes": "8031533", "tp_unid_cod": "22", "tp_unid": "Consultório Isolado", "cnpj": "53842194000139", "cnpj_mantenedora": "00000000000000", "cep": "37925000", "atende_sus": "0", "atendimento_ambulatorial": "1", "atendimento_hospitalar": "0", "urgencia_emergencia": "0", "natureza_juridica": "2062", "nome": "CLINICA DE PSICOLOGIA CLARISSA FREITAS"}, {"cnes": "8062498", "tp_unid_cod": "22", "tp_unid": "Consultório Isolado", "cnpj": "41404448000158", "cnpj_mantenedora": "00000000000000", "cep": "37925000", "atende_sus": "0", "atendimento_ambulatorial": "1", "atendimento_hospitalar": "0", "urgencia_emergencia": "0", "natureza_juridica": "2062", "nome": "RIZO CENTRO ODONTOLOGICO"}, {"cnes": "8070652", "tp_unid_cod": "22", "tp_unid": "Consultório Isolado", "cnpj": "62558263000178", "cnpj_mantenedora": "00000000000000", "cep": "37925000", "atende_sus": "0", "atendimento_ambulatorial": "1", "atendimento_hospitalar": "0", "urgencia_emergencia": "0", "natureza_juridica": "2062", "nome": "AFETO"}, {"cnes": "8093989", "tp_unid_cod": "22", "tp_unid": "Consultório Isolado", "cnpj": "62558165000130", "cnpj_mantenedora": "00000000000000", "cep": "37925000", "atende_sus": "0", "atendimento_ambulatorial": "1", "atendimento_hospitalar": "0", "urgencia_emergencia": "0", "natureza_juridica": "2135", "nome": "SERENALIS"}, {"cnes": "8111782", "tp_unid_cod": "22", "tp_unid": "Consultório Isolado", "cnpj": "44620583000129", "cnpj_mantenedora": "00000000000000", "cep": "37925000", "atende_sus": "0", "atendimento_ambulatorial": "1", "atendimento_hospitalar": "0", "urgencia_emergencia": "0", "natureza_juridica": "2062", "nome": "FERREIRA HOSTALACIO SERVICOS MEDICOS LTDA"}, {"cnes": "8129428", "tp_unid_cod": "22", "tp_unid": "Consultório Isolado", "cnpj": "34582917000244", "cnpj_mantenedora": "00000000000000", "cep": "37925000", "atende_sus": "0", "atendimento_ambulatorial": "1", "atendimento_hospitalar": "0", "urgencia_emergencia": "0", "natureza_juridica": "2062", "nome": "S D O B G LOPES ASSISTENCIA MEDICA"}, {"cnes": "8139806", "tp_unid_cod": "22", "tp_unid": "Consultório Isolado", "cnpj": "61550829000152", "cnpj_mantenedora": "00000000000000", "cep": "37925000", "atende_sus": "0", "atendimento_ambulatorial": "1", "atendimento_hospitalar": "0", "urgencia_emergencia": "0", "natureza_juridica": "2062", "nome": "BORBOLETANDO CLINICA DE REABILITACAO LTDA"}, {"cnes": "9056645", "tp_unid_cod": "22", "tp_unid": "Consultório Isolado", "cnpj": "00010217544630", "cnpj_mantenedora": "00000000000000", "cep": "37925000", "atende_sus": "0", "atendimento_ambulatorial": "1", "atendimento_hospitalar": "0", "urgencia_emergencia": "0", "natureza_juridica": "4000", "nome": "PATRICIA DE MELO CRUVINEL"}, {"cnes": "9079246", "tp_unid_cod": "22", "tp_unid": "Consultório Isolado", "cnpj": "71064539000586", "cnpj_mantenedora": "00000000000000", "cep": "37925000", "atende_sus": "1", "atendimento_ambulatorial": "1", "atendimento_hospitalar": "0", "urgencia_emergencia": "0", "natureza_juridica": "2143", "nome": "NUCLEO DE ATENCAO A SAUDE PIUMHI"}, {"cnes": "9140689", "tp_unid_cod": "22", "tp_unid": "Consultório Isolado", "cnpj": "18206935000194", "cnpj_mantenedora": "00000000000000", "cep": "37925000", "atende_sus": "0", "atendimento_ambulatorial": "1", "atendimento_hospitalar": "0", "urgencia_emergencia": "0", "natureza_juridica": "2062", "nome": "AFJ SERVICOS MEDICOS"}, {"cnes": "9144609", "tp_unid_cod": "22", "tp_unid": "Consultório Isolado", "cnpj": "00009569142766", "cnpj_mantenedora": "00000000000000", "cep": "37925000", "atende_sus": "0", "atendimento_ambulatorial": "1", "atendimento_hospitalar": "0", "urgencia_emergencia": "0", "natureza_juridica": "4000", "nome": "RUTE FERREIRA DE FREITAS GOMES"}, {"cnes": "9160086", "tp_unid_cod": "22", "tp_unid": "Consultório Isolado", "cnpj": "21944515000110", "cnpj_mantenedora": "00000000000000", "cep": "37925000", "atende_sus": "0", "atendimento_ambulatorial": "1", "atendimento_hospitalar": "0", "urgencia_emergencia": "0", "natureza_juridica": "2062", "nome": "FISIAC REABILITAR LTDA ME"}, {"cnes": "9179429", "tp_unid_cod": "22", "tp_unid": "Consultório Isolado", "cnpj": "24477851000279", "cnpj_mantenedora": "00000000000000", "cep": "37925000", "atende_sus": "0", "atendimento_ambulatorial": "1", "atendimento_hospitalar": "0", "urgencia_emergencia": "0", "natureza_juridica": "2062", "nome": "DR ATENDE"}, {"cnes": "9208046", "tp_unid_cod": "22", "tp_unid": "Consultório Isolado", "cnpj": "26967698000102", "cnpj_mantenedora": "00000000000000", "cep": "37925000", "atende_sus": "0", "atendimento_ambulatorial": "1", "atendimento_hospitalar": "0", "urgencia_emergencia": "0", "natureza_juridica": "2240", "nome": "CLINICA DO CORACAO E MULTIESPECIALIDADES"}, {"cnes": "9460705", "tp_unid_cod": "22", "tp_unid": "Consultório Isolado", "cnpj": "26965431000186", "cnpj_mantenedora": "00000000000000", "cep": "37925000", "atende_sus": "0", "atendimento_ambulatorial": "1", "atendimento_hospitalar": "0", "urgencia_emergencia": "0", "natureza_juridica": "2062", "nome": "GRUPO RECOMECO"}, {"cnes": "9696180", "tp_unid_cod": "36", "tp_unid": "Clínica/Centro de Especialidade", "cnpj": "19583793000147", "cnpj_mantenedora": "00000000000000", "cep": "37925000", "atende_sus": "1", "atendimento_ambulatorial": "1", "atendimento_hospitalar": "0", "urgencia_emergencia": "0", "natureza_juridica": "2062", "nome": "WS MEDICOS ASSOCIADOS"}, {"cnes": "9721088", "tp_unid_cod": "36", "tp_unid": "Clínica/Centro de Especialidade", "cnpj": "31487343000156", "cnpj_mantenedora": "00000000000000", "cep": "37925000", "atende_sus": "0", "atendimento_ambulatorial": "1", "atendimento_hospitalar": "0", "urgencia_emergencia": "0", "natureza_juridica": "2135", "nome": "MOVIMENT"}, {"cnes": "9737472", "tp_unid_cod": "36", "tp_unid": "Clínica/Centro de Especialidade", "cnpj": "18866976000107", "cnpj_mantenedora": "00000000000000", "cep": "37925000", "atende_sus": "1", "atendimento_ambulatorial": "1", "atendimento_hospitalar": "0", "urgencia_emergencia": "0", "natureza_juridica": "2062", "nome": "CLINICA MEDICA BARRIOS JESUS LTDA"}, {"cnes": "9905960", "tp_unid_cod": "22", "tp_unid": "Consultório Isolado", "cnpj": "12283462000142", "cnpj_mantenedora": "00000000000000", "cep": "37925000", "atende_sus": "0", "atendimento_ambulatorial": "1", "atendimento_hospitalar": "0", "urgencia_emergencia": "0", "natureza_juridica": "2062", "nome": "CLINICA FACE LTDA"}, {"cnes": "9966994", "tp_unid_cod": "22", "tp_unid": "Consultório Isolado", "cnpj": "03557966000112", "cnpj_mantenedora": "00000000000000", "cep": "37925000", "atende_sus": "1", "atendimento_ambulatorial": "1", "atendimento_hospitalar": "0", "urgencia_emergencia": "0", "natureza_juridica": "2240", "nome": "CLINICA DE OLHOS PIUMHI LTDA"}, {"cnes": "9967249", "tp_unid_cod": "22", "tp_unid": "Consultório Isolado", "cnpj": "04486406000187", "cnpj_mantenedora": "00000000000000", "cep": "37925000", "atende_sus": "0", "atendimento_ambulatorial": "1", "atendimento_hospitalar": "0", "urgencia_emergencia": "0", "natureza_juridica": "2062", "nome": "CLINICA DR WALLACE COSTA MOTA LTDA"}, {"cnes": "9967257", "tp_unid_cod": "22", "tp_unid": "Consultório Isolado", "cnpj": "08209129000116", "cnpj_mantenedora": "00000000000000", "cep": "37925000", "atende_sus": "0", "atendimento_ambulatorial": "1", "atendimento_hospitalar": "0", "urgencia_emergencia": "0", "natureza_juridica": "2062", "nome": "ODONTOLOGIA ESPECIALIZADA"}, {"cnes": "9967273", "tp_unid_cod": "22", "tp_unid": "Consultório Isolado", "cnpj": "10843843000103", "cnpj_mantenedora": "00000000000000", "cep": "37925000", "atende_sus": "0", "atendimento_ambulatorial": "1", "atendimento_hospitalar": "0", "urgencia_emergencia": "0", "natureza_juridica": "2062", "nome": "CLIMEP CLINICA MEDICA PIUMHI LTDA"}, {"cnes": "9967281", "tp_unid_cod": "22", "tp_unid": "Consultório Isolado", "cnpj": "11573166000113", "cnpj_mantenedora": "00000000000000", "cep": "37925000", "atende_sus": "0", "atendimento_ambulatorial": "1", "atendimento_hospitalar": "0", "urgencia_emergencia": "0", "natureza_juridica": "2062", "nome": "CLINICA OFTALMOLOGICA DR PAULO HENRIQUE FRIA SILVA EIRELI"}, {"cnes": "9982620", "tp_unid_cod": "22", "tp_unid": "Consultório Isolado", "cnpj": "26267111000152", "cnpj_mantenedora": "00000000000000", "cep": "37925000", "atende_sus": "1", "atendimento_ambulatorial": "1", "atendimento_hospitalar": "0", "urgencia_emergencia": "0", "natureza_juridica": "3999", "nome": "ASSOCIACAO DE AMPARO AOS PORTADORES DE CANCER DE PIUMHI E RE"}]}