{"ibge": 3153400, "codufmun": "315340", "fonte": "cnes_st_mg_202603.parquet", "total_no_municipio": 22, "total_relevante_generalista": 14, "por_tipo": {"Centro de Saúde / UBS": 7, "Clínica/Centro de Especialidade": 5, "Hospital Geral": 1, "Posto de Saúde": 1}, "estabelecimentos": [{"cnes": "0279307", "tp_unid_cod": "02", "tp_unid": "Centro de Saúde / UBS", "cnpj": "00000000000000", "cnpj_mantenedora": "18602060000140", "cep": "38750000", "atende_sus": "1", "atendimento_ambulatorial": "1", "atendimento_hospitalar": "0", "urgencia_emergencia": "0", "natureza_juridica": "1244", "nome": "UBS CONCEICAO DOS REIS OLIVEIRA"}, {"cnes": "2101432", "tp_unid_cod": "05", "tp_unid": "Hospital Geral", "cnpj": "00000000000000", "cnpj_mantenedora": "18602060000140", "cep": "38750000", "atende_sus": "1", "atendimento_ambulatorial": "1", "atendimento_hospitalar": "1", "urgencia_emergencia": "0", "natureza_juridica": "1244", "nome": "HOSPITAL MUNICIPAL DARCI JOSE FERNANDES"}, {"cnes": "2101467", "tp_unid_cod": "02", "tp_unid": "Centro de Saúde / UBS", "cnpj": "00000000000000", "cnpj_mantenedora": "18602060000140", "cep": "38750000", "atende_sus": "1", "atendimento_ambulatorial": "1", "atendimento_hospitalar": "0", "urgencia_emergencia": "0", "natureza_juridica": "1244", "nome": "UNIDADE BASICA DE SAUDE ZONA RURAL"}, {"cnes": "2101491", "tp_unid_cod": "02", "tp_unid": "Centro de Saúde / UBS", "cnpj": "00000000000000", "cnpj_mantenedora": "18602060000140", "cep": "38750000", "atende_sus": "1", "atendimento_ambulatorial": "1", "atendimento_hospitalar": "0", "urgencia_emergencia": "0", "natureza_juridica": "1244", "nome": "UNIDADE BASICA DE SAUDE PLANALTO"}, {"cnes": "2101513", "tp_unid_cod": "02", "tp_unid": "Centro de Saúde / UBS", "cnpj": "00000000000000", "cnpj_mantenedora": "18602060000140", "cep": "38750000", "atende_sus": "1", "atendimento_ambulatorial": "1", "atendimento_hospitalar": "0", "urgencia_emergencia": "1", "natureza_juridica": "1244", "nome": "CLINICA MUNICIPAL MONSENHOR JOSE GUIMARAES"}, {"cnes": "2101548", "tp_unid_cod": "02", "tp_unid": "Centro de Saúde / UBS", "cnpj": "00000000000000", "cnpj_mantenedora": "18602060000140", "cep": "38750000", "atende_sus": "1", "atendimento_ambulatorial": "1", "atendimento_hospitalar": "0", "urgencia_emergencia": "0", "natureza_juridica": "1244", "nome": "UNIDADE BASICA DE SAUDE ANDORINHAS"}, {"cnes": "3730654", "tp_unid_cod": "36", "tp_unid": "Clínica/Centro de Especialidade", "cnpj": "01517298000174", "cnpj_mantenedora": "00000000000000", "cep": "38750000", "atende_sus": "1", "atendimento_ambulatorial": "1", "atendimento_hospitalar": "0", "urgencia_emergencia": "0", "natureza_juridica": "3999", "nome": "APAE DE PRESIDENTE OLEGARIO"}, {"cnes": "3931935", "tp_unid_cod": "02", "tp_unid": "Centro de Saúde / UBS", "cnpj": "00000000000000", "cnpj_mantenedora": "18602060000140", "cep": "38750000", "atende_sus": "1", "atendimento_ambulatorial": "1", "atendimento_hospitalar": "0", "urgencia_emergencia": "0", "natureza_juridica": "1244", "nome": "UNIDADE BASICA DE SAUDE BILE GODINHO"}, {"cnes": "4793846", "tp_unid_cod": "36", "tp_unid": "Clínica/Centro de Especialidade", "cnpj": "55317979000118", "cnpj_mantenedora": "00000000000000", "cep": "38750000", "atende_sus": "1", "atendimento_ambulatorial": "1", "atendimento_hospitalar": "0", "urgencia_emergencia": "0", "natureza_juridica": "2062", "nome": "CLINICA VIVA MAIS"}, {"cnes": "4864050", "tp_unid_cod": "36", "tp_unid": "Clínica/Centro de Especialidade", "cnpj": "55825828000170", "cnpj_mantenedora": "00000000000000", "cep": "38750000", "atende_sus": "1", "atendimento_ambulatorial": "1", "atendimento_hospitalar": "0", "urgencia_emergencia": "0", "natureza_juridica": "2062", "nome": "CLINICA SAGRADA FAMILIA"}, {"cnes": "5445825", "tp_unid_cod": "36", "tp_unid": "Clínica/Centro de Especialidade", "cnpj": "57339017000195", "cnpj_mantenedora": "00000000000000", "cep": "38750000", "atende_sus": "0", "atendimento_ambulatorial": "1", "atendimento_hospitalar": "0", "urgencia_emergencia": "0", "natureza_juridica": "2062", "nome": "CLINICA CARDIOLOGICA DR MAX BOLIVAR"}, {"cnes": "5503574", "tp_unid_cod": "36", "tp_unid": "Clínica/Centro de Especialidade", "cnpj": "11963887000210", "cnpj_mantenedora": "00000000000000", "cep": "38750000", "atende_sus": "1", "atendimento_ambulatorial": "1", "atendimento_hospitalar": "0", "urgencia_emergencia": "0", "natureza_juridica": "2062", "nome": "CLINICA L L IMAGEM E OFTALMOLOGIA"}, {"cnes": "6434878", "tp_unid_cod": "02", "tp_unid": "Centro de Saúde / UBS", "cnpj": "00000000000000", "cnpj_mantenedora": "18602060000140", "cep": "38750000", "atende_sus": "1", "atendimento_ambulatorial": "1", "atendimento_hospitalar": "0", "urgencia_emergencia": "0", "natureza_juridica": "1244", "nome": "UNIDADE BASICA DE SAUDE DONA ZEZE"}, {"cnes": "6910610", "tp_unid_cod": "01", "tp_unid": "Posto de Saúde", "cnpj": "00000000000000", "cnpj_mantenedora": "05487631000109", "cep": "38750000", "atende_sus": "1", "atendimento_ambulatorial": "1", "atendimento_hospitalar": "0", "urgencia_emergencia": "0", "natureza_juridica": "1023", "nome": "PRESIDIO DE PRESIDENTE OLEGARIO"}]}