{"ibge": 3156809, "codufmun": "315680", "fonte": "cnes_st_mg_202603.parquet", "total_no_municipio": 25, "total_relevante_generalista": 18, "por_tipo": {"Centro de Saúde / UBS": 6, "Consultório Isolado": 6, "Policlínica": 3, "Clínica/Centro de Especialidade": 2, "Hospital Geral": 1}, "estabelecimentos": [{"cnes": "0839418", "tp_unid_cod": "04", "tp_unid": "Policlínica", "cnpj": "04503677000101", "cnpj_mantenedora": "00000000000000", "cep": "39750000", "atende_sus": "0", "atendimento_ambulatorial": "1", "atendimento_hospitalar": "0", "urgencia_emergencia": "0", "natureza_juridica": "3999", "nome": "APAE DE SABINOPOLIS"}, {"cnes": "2134659", "tp_unid_cod": "02", "tp_unid": "Centro de Saúde / UBS", "cnpj": "00000000000000", "cnpj_mantenedora": "18307454000175", "cep": "39750000", "atende_sus": "1", "atendimento_ambulatorial": "1", "atendimento_hospitalar": "0", "urgencia_emergencia": "0", "natureza_juridica": "1244", "nome": "PSF MONSENHOR AMANTINO SABINOPOLIS"}, {"cnes": "2134667", "tp_unid_cod": "02", "tp_unid": "Centro de Saúde / UBS", "cnpj": "00000000000000", "cnpj_mantenedora": "18307454000175", "cep": "39750000", "atende_sus": "1", "atendimento_ambulatorial": "1", "atendimento_hospitalar": "0", "urgencia_emergencia": "0", "natureza_juridica": "1244", "nome": "PSF CENTRAL SABINOPOLIS"}, {"cnes": "2134675", "tp_unid_cod": "02", "tp_unid": "Centro de Saúde / UBS", "cnpj": "00000000000000", "cnpj_mantenedora": "18307454000175", "cep": "39753000", "atende_sus": "1", "atendimento_ambulatorial": "1", "atendimento_hospitalar": "0", "urgencia_emergencia": "0", "natureza_juridica": "1244", "nome": "PSF SAO JOSE SABINOPOLIS"}, {"cnes": "2134756", "tp_unid_cod": "02", "tp_unid": "Centro de Saúde / UBS", "cnpj": "00000000000000", "cnpj_mantenedora": "18307454000175", "cep": "39750000", "atende_sus": "1", "atendimento_ambulatorial": "1", "atendimento_hospitalar": "0", "urgencia_emergencia": "0", "natureza_juridica": "1244", "nome": "PSF SANTA RITA SABINOPOLIS"}, {"cnes": "2134764", "tp_unid_cod": "02", "tp_unid": "Centro de Saúde / UBS", "cnpj": "00000000000000", "cnpj_mantenedora": "18307454000175", "cep": "39750000", "atende_sus": "1", "atendimento_ambulatorial": "1", "atendimento_hospitalar": "0", "urgencia_emergencia": "0", "natureza_juridica": "1244", "nome": "PSF CRISTAL SABINOPOLIS"}, {"cnes": "2135914", "tp_unid_cod": "05", "tp_unid": "Hospital Geral", "cnpj": "24331027000125", "cnpj_mantenedora": "00000000000000", "cep": "39750000", "atende_sus": "1", "atendimento_ambulatorial": "1", "atendimento_hospitalar": "1", "urgencia_emergencia": "1", "natureza_juridica": "3999", "nome": "HOSPITAL SAO SEBASTIAO DE SABINOPOLIS"}, {"cnes": "2934183", "tp_unid_cod": "22", "tp_unid": "Consultório Isolado", "cnpj": "46148199000109", "cnpj_mantenedora": "00000000000000", "cep": "39750000", "atende_sus": "0", "atendimento_ambulatorial": "1", "atendimento_hospitalar": "0", "urgencia_emergencia": "0", "natureza_juridica": "2240", "nome": "CLINICA MEDICA PINHO TAVARES"}, {"cnes": "4043219", "tp_unid_cod": "04", "tp_unid": "Policlínica", "cnpj": "00000000000000", "cnpj_mantenedora": "18307454000175", "cep": "39750000", "atende_sus": "1", "atendimento_ambulatorial": "1", "atendimento_hospitalar": "0", "urgencia_emergencia": "0", "natureza_juridica": "1244", "nome": "POLICLINICA DR ALEXANDRE DE PINHO TAVARES"}, {"cnes": "4429885", "tp_unid_cod": "22", "tp_unid": "Consultório Isolado", "cnpj": "51765730000114", "cnpj_mantenedora": "00000000000000", "cep": "39750000", "atende_sus": "0", "atendimento_ambulatorial": "1", "atendimento_hospitalar": "0", "urgencia_emergencia": "0", "natureza_juridica": "2062", "nome": "CLINICA PINHO PIMENTA"}, {"cnes": "5603552", "tp_unid_cod": "22", "tp_unid": "Consultório Isolado", "cnpj": "01162710000180", "cnpj_mantenedora": "00000000000000", "cep": "39750000", "atende_sus": "0", "atendimento_ambulatorial": "1", "atendimento_hospitalar": "0", "urgencia_emergencia": "0", "natureza_juridica": "2062", "nome": "CLINICA PRO VIDA"}, {"cnes": "6538940", "tp_unid_cod": "02", "tp_unid": "Centro de Saúde / UBS", "cnpj": "00000000000000", "cnpj_mantenedora": "18307454000175", "cep": "39750000", "atende_sus": "1", "atendimento_ambulatorial": "1", "atendimento_hospitalar": "0", "urgencia_emergencia": "0", "natureza_juridica": "1244", "nome": "ESF SAO JUDAS TADEU"}, {"cnes": "6558917", "tp_unid_cod": "36", "tp_unid": "Clínica/Centro de Especialidade", "cnpj": "11873983000197", "cnpj_mantenedora": "00000000000000", "cep": "39750000", "atende_sus": "0", "atendimento_ambulatorial": "1", "atendimento_hospitalar": "0", "urgencia_emergencia": "0", "natureza_juridica": "2062", "nome": "CLINICA CONFIO"}, {"cnes": "7651104", "tp_unid_cod": "22", "tp_unid": "Consultório Isolado", "cnpj": "21528155000175", "cnpj_mantenedora": "00000000000000", "cep": "39750000", "atende_sus": "0", "atendimento_ambulatorial": "1", "atendimento_hospitalar": "0", "urgencia_emergencia": "0", "natureza_juridica": "2062", "nome": "CLINICA CRESCER"}, {"cnes": "7651112", "tp_unid_cod": "04", "tp_unid": "Policlínica", "cnpj": "20275611000150", "cnpj_mantenedora": "00000000000000", "cep": "39750000", "atende_sus": "0", "atendimento_ambulatorial": "1", "atendimento_hospitalar": "0", "urgencia_emergencia": "0", "natureza_juridica": "2062", "nome": "CLINICA DR FRANCIOLI OTYLIO BERTOLINO LTDA ME"}, {"cnes": "7919409", "tp_unid_cod": "36", "tp_unid": "Clínica/Centro de Especialidade", "cnpj": "18162664000112", "cnpj_mantenedora": "00000000000000", "cep": "39750000", "atende_sus": "0", "atendimento_ambulatorial": "1", "atendimento_hospitalar": "0", "urgencia_emergencia": "0", "natureza_juridica": "2062", "nome": "CLINICA DR FLAVIANO DE PINHO AMARAL EIRELI"}, {"cnes": "9136495", "tp_unid_cod": "22", "tp_unid": "Consultório Isolado", "cnpj": "19877203000199", "cnpj_mantenedora": "00000000000000", "cep": "39750000", "atende_sus": "0", "atendimento_ambulatorial": "1", "atendimento_hospitalar": "0", "urgencia_emergencia": "0", "natureza_juridica": "2062", "nome": "SABICLINICA"}, {"cnes": "9169849", "tp_unid_cod": "22", "tp_unid": "Consultório Isolado", "cnpj": "23776536000107", "cnpj_mantenedora": "00000000000000", "cep": "39750000", "atende_sus": "0", "atendimento_ambulatorial": "1", "atendimento_hospitalar": "0", "urgencia_emergencia": "0", "natureza_juridica": "2240", "nome": "CLINICA SORRIDENTE"}]}