{"ibge": 3158904, "codufmun": "315890", "fonte": "cnes_st_mg_202603.parquet", "total_no_municipio": 18, "total_relevante_generalista": 9, "por_tipo": {"Consultório Isolado": 3, "Posto de Saúde": 3, "Centro de Saúde / UBS": 1, "Clínica/Centro de Especialidade": 1, "Pronto Atendimento": 1}, "estabelecimentos": [{"cnes": "2115263", "tp_unid_cod": "01", "tp_unid": "Posto de Saúde", "cnpj": "00000000000000", "cnpj_mantenedora": "18385146000168", "cep": "36940000", "atende_sus": "1", "atendimento_ambulatorial": "1", "atendimento_hospitalar": "0", "urgencia_emergencia": "0", "natureza_juridica": "1244", "nome": "UNIDADE DE SAUDE DA FAMILIA SAO LUCAS SANTANA MANHUACU"}, {"cnes": "2115298", "tp_unid_cod": "01", "tp_unid": "Posto de Saúde", "cnpj": "00000000000000", "cnpj_mantenedora": "18385146000168", "cep": "36940000", "atende_sus": "1", "atendimento_ambulatorial": "1", "atendimento_hospitalar": "0", "urgencia_emergencia": "0", "natureza_juridica": "1244", "nome": "POSTO DE SAUDE SANTA QUITERIA SANTANA DO MANHUACU PSF"}, {"cnes": "2115468", "tp_unid_cod": "02", "tp_unid": "Centro de Saúde / UBS", "cnpj": "00000000000000", "cnpj_mantenedora": "18385146000168", "cep": "36940000", "atende_sus": "1", "atendimento_ambulatorial": "1", "atendimento_hospitalar": "0", "urgencia_emergencia": "0", "natureza_juridica": "1244", "nome": "CENTRO DE SAUDE DE SANTANA DO MANHUACU"}, {"cnes": "4195159", "tp_unid_cod": "36", "tp_unid": "Clínica/Centro de Especialidade", "cnpj": "00000000000000", "cnpj_mantenedora": "18385146000168", "cep": "36940000", "atende_sus": "1", "atendimento_ambulatorial": "1", "atendimento_hospitalar": "0", "urgencia_emergencia": "0", "natureza_juridica": "1244", "nome": "CENTRO DE REABILITACAO E FISIOTERAPIA"}, {"cnes": "5686628", "tp_unid_cod": "73", "tp_unid": "Pronto Atendimento", "cnpj": "00000000000000", "cnpj_mantenedora": "18385146000168", "cep": "36940000", "atende_sus": "1", "atendimento_ambulatorial": "0", "atendimento_hospitalar": "0", "urgencia_emergencia": "1", "natureza_juridica": "1244", "nome": "PRONTO ATENDIMENTO DE SANTANA DO MANHUACU"}, {"cnes": "7269234", "tp_unid_cod": "01", "tp_unid": "Posto de Saúde", "cnpj": "00000000000000", "cnpj_mantenedora": "18385146000168", "cep": "36940000", "atende_sus": "1", "atendimento_ambulatorial": "1", "atendimento_hospitalar": "0", "urgencia_emergencia": "0", "natureza_juridica": "1244", "nome": "ESF SANTA ANA"}, {"cnes": "7946856", "tp_unid_cod": "22", "tp_unid": "Consultório Isolado", "cnpj": "08236241000227", "cnpj_mantenedora": "00000000000000", "cep": "36940000", "atende_sus": "0", "atendimento_ambulatorial": "1", "atendimento_hospitalar": "0", "urgencia_emergencia": "0", "natureza_juridica": "2240", "nome": "COI"}, {"cnes": "8101493", "tp_unid_cod": "22", "tp_unid": "Consultório Isolado", "cnpj": "00012914949600", "cnpj_mantenedora": "00000000000000", "cep": "36940000", "atende_sus": "0", "atendimento_ambulatorial": "1", "atendimento_hospitalar": "0", "urgencia_emergencia": "0", "natureza_juridica": "4000", "nome": "KARINA FREITAS PEDIATRIA"}, {"cnes": "8176671", "tp_unid_cod": "22", "tp_unid": "Consultório Isolado", "cnpj": "65311071000150", "cnpj_mantenedora": "00000000000000", "cep": "36940000", "atende_sus": "0", "atendimento_ambulatorial": "1", "atendimento_hospitalar": "0", "urgencia_emergencia": "0", "natureza_juridica": "2135", "nome": "DRA CAROLINA DE SOUZA ASSIS"}]}